[{"Comas":"Afaahiti","Ile":"Tahiti","TrancheAge":"0 - 13 ans","Sexe":"Femme","StatutMarital":"Non concerne","StatutOccupation":"Propriétaire du sol et du logement","StatutMaritalFreq":0.5007,"AgeMin":0,"AgeMax":13,"Alcool":162855.1911,"Tabac":98468.2848},{"Comas":"Afaahiti","Ile":"Tahiti","TrancheAge":"0 - 13 ans","Sexe":"Homme","StatutMarital":"Non concerne","StatutOccupation":"Propriétaire du sol et du logement","StatutMaritalFreq":0.4993,"AgeMin":0,"AgeMax":13,"Alcool":162855.1911,"Tabac":98468.2848},{"Comas":"Afaahiti","Ile":"Tahiti","TrancheAge":"14 - 19 ans","Sexe":"Femme","StatutMarital":"Celibataire","StatutOccupation":"Propriétaire du sol et du logement","StatutMaritalFreq":0.4712,"AgeMin":14,"AgeMax":19,"Alcool":162855.1911,"Tabac":98468.2848},{"Comas":"Afaahiti","Ile":"Tahiti","TrancheAge":"14 - 19 ans","Sexe":"Homme","StatutMarital":"Celibataire","StatutOccupation":"Propriétaire du sol et du logement","StatutMaritalFreq":0.5288,"AgeMin":14,"AgeMax":19,"Alcool":162855.1911,"Tabac":98468.2848},{"Comas":"Afaahiti","Ile":"Tahiti","TrancheAge":"20 - 29 ans","Sexe":"Femme","StatutMarital":"Celibataire","StatutOccupation":"Propriétaire du sol et du logement","StatutMaritalFreq":0.5076,"AgeMin":20,"AgeMax":29,"Alcool":162855.1911,"Tabac":98468.2848},{"Comas":"Afaahiti","Ile":"Tahiti","TrancheAge":"20 - 29 ans","Sexe":"Homme","StatutMarital":"Celibataire","StatutOccupation":"Propriétaire du sol et du logement","StatutMaritalFreq":0.4924,"AgeMin":20,"AgeMax":29,"Alcool":162855.1911,"Tabac":98468.2848},{"Comas":"Afaahiti","Ile":"Tahiti","TrancheAge":"30 - 39 ans","Sexe":"Femme","StatutMarital":"Celibataire","StatutOccupation":"Propriétaire du sol et du logement","StatutMaritalFreq":0.5255,"AgeMin":30,"AgeMax":39,"Alcool":211988.5356,"Tabac":60654.7456},{"Comas":"Afaahiti","Ile":"Tahiti","TrancheAge":"30 - 39 ans","Sexe":"Homme","StatutMarital":"Celibataire","StatutOccupation":"Propriétaire du sol et du logement","StatutMaritalFreq":0.4745,"AgeMin":30,"AgeMax":39,"Alcool":139114.9976,"Tabac":56590.7585},{"Comas":"Afaahiti","Ile":"Tahiti","TrancheAge":"40 - 49 ans","Sexe":"Femme","StatutMarital":"Marie","StatutOccupation":"Propriétaire du sol et du logement","StatutMaritalFreq":0.4841,"AgeMin":40,"AgeMax":49,"Alcool":202710.0224,"Tabac":299787.0268},{"Comas":"Afaahiti","Ile":"Tahiti","TrancheAge":"40 - 49 ans","Sexe":"Homme","StatutMarital":"Marie","StatutOccupation":"Propriétaire du sol et du logement","StatutMaritalFreq":0.5159,"AgeMin":40,"AgeMax":49,"Alcool":64683.1667,"Tabac":48210.8167},{"Comas":"Afaahiti","Ile":"Tahiti","TrancheAge":"50 - 59 ans","Sexe":"Femme","StatutMarital":"Marie","StatutOccupation":"Propriétaire du sol et du logement","StatutMaritalFreq":0.4831,"AgeMin":50,"AgeMax":59,"Alcool":141684.1036,"Tabac":95866.2497},{"Comas":"Afaahiti","Ile":"Tahiti","TrancheAge":"50 - 59 ans","Sexe":"Homme","StatutMarital":"Marie","StatutOccupation":"Propriétaire du sol et du logement","StatutMaritalFreq":0.5169,"AgeMin":50,"AgeMax":59,"Alcool":72475.5909,"Tabac":103030.1083},{"Comas":"Afaahiti","Ile":"Tahiti","TrancheAge":"60 ans +","Sexe":"Femme","StatutMarital":"Marie","StatutOccupation":"Propriétaire du sol et du logement","StatutMaritalFreq":0.4764,"AgeMin":60,"AgeMax":150,"Alcool":91509.2128,"Tabac":78589.352},{"Comas":"Afaahiti","Ile":"Tahiti","TrancheAge":"60 ans +","Sexe":"Homme","StatutMarital":"Marie","StatutOccupation":"Propriétaire du sol et du logement","StatutMaritalFreq":0.5236,"AgeMin":60,"AgeMax":150,"Alcool":107986.1184,"Tabac":56066.4738},{"Comas":"Afaahiti","Ile":"Tahiti","Sexe":"Femme","StatutMarital":"Marie","StatutOccupation":"Propriétaire du sol et du logement","StatutMaritalFreq":1,"AgeMax":150,"Alcool":162855.1911,"Tabac":98468.2848},{"Comas":"Arue","Ile":"Tahiti","TrancheAge":"0 - 13 ans","Sexe":"Femme","StatutMarital":"Non concerne","StatutOccupation":"Propriétaire du sol et du logement","StatutMaritalFreq":0.5091,"AgeMin":0,"AgeMax":13,"Alcool":162855.1911,"Tabac":98468.2848},{"Comas":"Arue","Ile":"Tahiti","TrancheAge":"0 - 13 ans","Sexe":"Homme","StatutMarital":"Non concerne","StatutOccupation":"Propriétaire du sol et du logement","StatutMaritalFreq":0.4909,"AgeMin":0,"AgeMax":13,"Alcool":162855.1911,"Tabac":98468.2848},{"Comas":"Arue","Ile":"Tahiti","TrancheAge":"14 - 19 ans","Sexe":"Femme","StatutMarital":"Celibataire","StatutOccupation":"Propriétaire du sol et du logement","StatutMaritalFreq":0.4895,"AgeMin":14,"AgeMax":19,"Alcool":162855.1911,"Tabac":98468.2848},{"Comas":"Arue","Ile":"Tahiti","TrancheAge":"14 - 19 ans","Sexe":"Homme","StatutMarital":"Celibataire","StatutOccupation":"Propriétaire du sol et du logement","StatutMaritalFreq":0.5105,"AgeMin":14,"AgeMax":19,"Alcool":162855.1911,"Tabac":98468.2848},{"Comas":"Arue","Ile":"Tahiti","TrancheAge":"20 - 29 ans","Sexe":"Femme","StatutMarital":"Celibataire","StatutOccupation":"Propriétaire du sol et du logement","StatutMaritalFreq":0.4799,"AgeMin":20,"AgeMax":29,"Alcool":162855.1911,"Tabac":98468.2848},{"Comas":"Arue","Ile":"Tahiti","TrancheAge":"20 - 29 ans","Sexe":"Homme","StatutMarital":"Celibataire","StatutOccupation":"Propriétaire du sol et du logement","StatutMaritalFreq":0.5201,"AgeMin":20,"AgeMax":29,"Alcool":304556.999,"Tabac":249958.7552},{"Comas":"Arue","Ile":"Tahiti","TrancheAge":"30 - 39 ans","Sexe":"Femme","StatutMarital":"Celibataire","StatutOccupation":"Propriétaire du sol et du logement","StatutMaritalFreq":0.5316,"AgeMin":30,"AgeMax":39,"Alcool":187035.8958,"Tabac":196572.5025},{"Comas":"Arue","Ile":"Tahiti","TrancheAge":"30 - 39 ans","Sexe":"Homme","StatutMarital":"Celibataire","StatutOccupation":"Propriétaire du sol et du logement","StatutMaritalFreq":0.4684,"AgeMin":30,"AgeMax":39,"Alcool":98177.9831,"Tabac":40885.7315},{"Comas":"Arue","Ile":"Tahiti","TrancheAge":"40 - 49 ans","Sexe":"Femme","StatutMarital":"Marie","StatutOccupation":"Propriétaire du sol et du logement","StatutMaritalFreq":0.4959,"AgeMin":40,"AgeMax":49,"Alcool":112284.4419,"Tabac":51538.7218},{"Comas":"Arue","Ile":"Tahiti","TrancheAge":"40 - 49 ans","Sexe":"Homme","StatutMarital":"Marie","StatutOccupation":"Propriétaire du sol et du logement","StatutMaritalFreq":0.5041,"AgeMin":40,"AgeMax":49,"Alcool":81365.4792,"Tabac":206028.8285},{"Comas":"Arue","Ile":"Tahiti","TrancheAge":"50 - 59 ans","Sexe":"Femme","StatutMarital":"Marie","StatutOccupation":"Propriétaire du sol et du logement","StatutMaritalFreq":0.4783,"AgeMin":50,"AgeMax":59,"Alcool":183868.0201,"Tabac":216189.3152},{"Comas":"Arue","Ile":"Tahiti","TrancheAge":"50 - 59 ans","Sexe":"Homme","StatutMarital":"Marie","StatutOccupation":"Propriétaire du sol et du logement","StatutMaritalFreq":0.5217,"AgeMin":50,"AgeMax":59,"Alcool":86928.0542,"Tabac":45178.7385},{"Comas":"Arue","Ile":"Tahiti","TrancheAge":"60 ans +","Sexe":"Femme","StatutMarital":"Marie","StatutOccupation":"Propriétaire du sol et du logement","StatutMaritalFreq":0.533,"AgeMin":60,"AgeMax":150,"Alcool":506079.4414,"Tabac":107134.7914},{"Comas":"Arue","Ile":"Tahiti","TrancheAge":"60 ans +","Sexe":"Homme","StatutMarital":"Marie","StatutOccupation":"Propriétaire du sol et du logement","StatutMaritalFreq":0.467,"AgeMin":60,"AgeMax":150,"Alcool":79151.3771,"Tabac":301217.7961},{"Comas":"Arue","Ile":"Tahiti","Sexe":"Homme","StatutMarital":"Marie","StatutOccupation":"Propriétaire du sol et du logement","StatutMaritalFreq":1,"AgeMax":150,"Alcool":162855.1911,"Tabac":98468.2848},{"Comas":"Faaa","Ile":"Tahiti","TrancheAge":"0 - 13 ans","Sexe":"Femme","StatutMarital":"Non concerne","StatutOccupation":"Propriétaire du sol et du logement","StatutMaritalFreq":0.4887,"AgeMin":0,"AgeMax":13,"Alcool":162855.1911,"Tabac":98468.2848},{"Comas":"Faaa","Ile":"Tahiti","TrancheAge":"0 - 13 ans","Sexe":"Homme","StatutMarital":"Non concerne","StatutOccupation":"Propriétaire du sol et du logement","StatutMaritalFreq":0.5113,"AgeMin":0,"AgeMax":13,"Alcool":162855.1911,"Tabac":98468.2848},{"Comas":"Faaa","Ile":"Tahiti","TrancheAge":"14 - 19 ans","Sexe":"Femme","StatutMarital":"Celibataire","StatutOccupation":"Propriétaire du sol et du logement","StatutMaritalFreq":0.501,"AgeMin":14,"AgeMax":19,"Alcool":162855.1911,"Tabac":98468.2848},{"Comas":"Faaa","Ile":"Tahiti","TrancheAge":"14 - 19 ans","Sexe":"Homme","StatutMarital":"Celibataire","StatutOccupation":"Propriétaire du sol et du logement","StatutMaritalFreq":0.499,"AgeMin":14,"AgeMax":19,"Alcool":162855.1911,"Tabac":98468.2848},{"Comas":"Faaa","Ile":"Tahiti","TrancheAge":"20 - 29 ans","Sexe":"Femme","StatutMarital":"Celibataire","StatutOccupation":"Propriétaire du sol et du logement","StatutMaritalFreq":0.4959,"AgeMin":20,"AgeMax":29,"Alcool":293258.8754,"Tabac":287572.28},{"Comas":"Faaa","Ile":"Tahiti","TrancheAge":"20 - 29 ans","Sexe":"Homme","StatutMarital":"Celibataire","StatutOccupation":"Propriétaire du sol et du logement","StatutMaritalFreq":0.5041,"AgeMin":20,"AgeMax":29,"Alcool":278825.3798,"Tabac":98468.2848},{"Comas":"Faaa","Ile":"Tahiti","TrancheAge":"30 - 39 ans","Sexe":"Femme","StatutMarital":"Celibataire","StatutOccupation":"Propriétaire du sol et du logement","StatutMaritalFreq":0.483,"AgeMin":30,"AgeMax":39,"Alcool":402015.3929,"Tabac":238833.6608},{"Comas":"Faaa","Ile":"Tahiti","TrancheAge":"30 - 39 ans","Sexe":"Homme","StatutMarital":"Celibataire","StatutOccupation":"Propriétaire du sol et du logement","StatutMaritalFreq":0.517,"AgeMin":30,"AgeMax":39,"Alcool":82526.713,"Tabac":43241.035},{"Comas":"Faaa","Ile":"Tahiti","TrancheAge":"40 - 49 ans","Sexe":"Femme","StatutMarital":"Marie","StatutOccupation":"Propriétaire du sol et du logement","StatutMaritalFreq":0.4828,"AgeMin":40,"AgeMax":49,"Alcool":156684.6558,"Tabac":120362.1968},{"Comas":"Faaa","Ile":"Tahiti","TrancheAge":"40 - 49 ans","Sexe":"Homme","StatutMarital":"Celibataire","StatutOccupation":"Propriétaire du sol et du logement","StatutMaritalFreq":0.5172,"AgeMin":40,"AgeMax":49,"Alcool":53685.8843,"Tabac":34920.4607},{"Comas":"Faaa","Ile":"Tahiti","TrancheAge":"50 - 59 ans","Sexe":"Femme","StatutMarital":"Marie","StatutOccupation":"Propriétaire du sol et du logement","StatutMaritalFreq":0.4755,"AgeMin":50,"AgeMax":59,"Alcool":241605.195,"Tabac":208771.524},{"Comas":"Faaa","Ile":"Tahiti","TrancheAge":"50 - 59 ans","Sexe":"Homme","StatutMarital":"Marie","StatutOccupation":"Propriétaire du sol et du logement","StatutMaritalFreq":0.5245,"AgeMin":50,"AgeMax":59,"Alcool":56395.1712,"Tabac":35170.6675},{"Comas":"Faaa","Ile":"Tahiti","TrancheAge":"60 ans +","Sexe":"Femme","StatutMarital":"Marie","StatutOccupation":"Propriétaire du sol et du logement","StatutMaritalFreq":0.5122,"AgeMin":60,"AgeMax":150,"Alcool":311543.2813,"Tabac":142699.0918},{"Comas":"Faaa","Ile":"Tahiti","TrancheAge":"60 ans +","Sexe":"Homme","StatutMarital":"Marie","StatutOccupation":"Propriétaire du sol et du logement","StatutMaritalFreq":0.4878,"AgeMin":60,"AgeMax":150,"Alcool":56252.6296,"Tabac":58953.3799},{"Comas":"Faaa","Ile":"Tahiti","Sexe":"Femme","StatutMarital":"Veuf,veuve","StatutOccupation":"Propriétaire du logement et terrain pris en location","StatutMaritalFreq":0.6667,"AgeMax":150,"Alcool":162855.1911,"Tabac":98468.2848},{"Comas":"Faaa","Ile":"Tahiti","Sexe":"Homme","StatutMarital":"Marie","StatutOccupation":"Propriétaire du logement et terrain pris en location","StatutMaritalFreq":0.3333,"AgeMax":150,"Alcool":162855.1911,"Tabac":98468.2848},{"Comas":"Faaone","Ile":"Tahiti","TrancheAge":"0 - 13 ans","Sexe":"Femme","StatutMarital":"Non concerne","StatutOccupation":"Propriétaire du sol et du logement","StatutMaritalFreq":0.4165,"AgeMin":0,"AgeMax":13,"Alcool":162855.1911,"Tabac":98468.2848},{"Comas":"Faaone","Ile":"Tahiti","TrancheAge":"0 - 13 ans","Sexe":"Homme","StatutMarital":"Non concerne","StatutOccupation":"Propriétaire du sol et du logement","StatutMaritalFreq":0.5835,"AgeMin":0,"AgeMax":13,"Alcool":162855.1911,"Tabac":98468.2848},{"Comas":"Faaone","Ile":"Tahiti","TrancheAge":"14 - 19 ans","Sexe":"Femme","StatutMarital":"Celibataire","StatutOccupation":"Propriétaire du sol et du logement","StatutMaritalFreq":0.4449,"AgeMin":14,"AgeMax":19,"Alcool":162855.1911,"Tabac":98468.2848},{"Comas":"Faaone","Ile":"Tahiti","TrancheAge":"14 - 19 ans","Sexe":"Homme","StatutMarital":"Celibataire","StatutOccupation":"Propriétaire du sol et du logement","StatutMaritalFreq":0.5551,"AgeMin":14,"AgeMax":19,"Alcool":162855.1911,"Tabac":98468.2848},{"Comas":"Faaone","Ile":"Tahiti","TrancheAge":"20 - 29 ans","Sexe":"Femme","StatutMarital":"Celibataire","StatutOccupation":"Propriétaire du sol et du logement","StatutMaritalFreq":0.5,"AgeMin":20,"AgeMax":29,"Alcool":162855.1911,"Tabac":64077.364},{"Comas":"Faaone","Ile":"Tahiti","TrancheAge":"20 - 29 ans","Sexe":"Homme","StatutMarital":"Celibataire","StatutOccupation":"Propriétaire du sol et du logement","StatutMaritalFreq":0.5,"AgeMin":20,"AgeMax":29,"Alcool":162855.1911,"Tabac":71981.0664},{"Comas":"Faaone","Ile":"Tahiti","TrancheAge":"30 - 39 ans","Sexe":"Femme","StatutMarital":"Celibataire","StatutOccupation":"Propriétaire du sol et du logement","StatutMaritalFreq":0.5214,"AgeMin":30,"AgeMax":39,"Alcool":162855.1911,"Tabac":65948.6294},{"Comas":"Faaone","Ile":"Tahiti","TrancheAge":"30 - 39 ans","Sexe":"Homme","StatutMarital":"Celibataire","StatutOccupation":"Propriétaire du sol et du logement","StatutMaritalFreq":0.4786,"AgeMin":30,"AgeMax":39,"Alcool":63058.895,"Tabac":65948.6294},{"Comas":"Faaone","Ile":"Tahiti","TrancheAge":"40 - 49 ans","Sexe":"Femme","StatutMarital":"Marie","StatutOccupation":"Propriétaire du sol et du logement","StatutMaritalFreq":0.4481,"AgeMin":40,"AgeMax":49,"Alcool":162855.1911,"Tabac":98468.2848},{"Comas":"Faaone","Ile":"Tahiti","TrancheAge":"40 - 49 ans","Sexe":"Homme","StatutMarital":"Celibataire","StatutOccupation":"Propriétaire du sol et du logement","StatutMaritalFreq":0.5519,"AgeMin":40,"AgeMax":49,"Alcool":162855.1911,"Tabac":74146.3795},{"Comas":"Faaone","Ile":"Tahiti","TrancheAge":"50 - 59 ans","Sexe":"Femme","StatutMarital":"Marie","StatutOccupation":"Propriétaire du sol et du logement","StatutMaritalFreq":0.4473,"AgeMin":50,"AgeMax":59,"Alcool":162855.1911,"Tabac":98468.2848},{"Comas":"Faaone","Ile":"Tahiti","TrancheAge":"50 - 59 ans","Sexe":"Homme","StatutMarital":"Marie","StatutOccupation":"Propriétaire du sol et du logement","StatutMaritalFreq":0.5527,"AgeMin":50,"AgeMax":59,"Alcool":67417.1183,"Tabac":25283.9616},{"Comas":"Faaone","Ile":"Tahiti","TrancheAge":"60 ans +","Sexe":"Femme","StatutMarital":"Marie","StatutOccupation":"Propriétaire du sol et du logement","StatutMaritalFreq":0.4833,"AgeMin":60,"AgeMax":150,"Alcool":162855.1911,"Tabac":34683.2252},{"Comas":"Faaone","Ile":"Tahiti","TrancheAge":"60 ans +","Sexe":"Homme","StatutMarital":"Marie","StatutOccupation":"Propriétaire du sol et du logement","StatutMaritalFreq":0.5167,"AgeMin":60,"AgeMax":150,"Alcool":70291.1448,"Tabac":98468.2848},{"Comas":"Faaone","Ile":"Tahiti","Sexe":"Homme","StatutMarital":"Veuf,veuve","StatutOccupation":"Propriétaire du sol et du logement","StatutMaritalFreq":1,"AgeMax":150,"Alcool":162855.1911,"Tabac":98468.2848},{"Comas":"Hitiaa","Ile":"Tahiti","TrancheAge":"0 - 13 ans","Sexe":"Femme","StatutMarital":"Non concerne","StatutOccupation":"Propriétaire du sol et du logement","StatutMaritalFreq":0.4922,"AgeMin":0,"AgeMax":13,"Alcool":162855.1911,"Tabac":98468.2848},{"Comas":"Hitiaa","Ile":"Tahiti","TrancheAge":"0 - 13 ans","Sexe":"Homme","StatutMarital":"Non concerne","StatutOccupation":"Propriétaire du sol et du logement","StatutMaritalFreq":0.5078,"AgeMin":0,"AgeMax":13,"Alcool":162855.1911,"Tabac":98468.2848},{"Comas":"Hitiaa","Ile":"Tahiti","TrancheAge":"14 - 19 ans","Sexe":"Femme","StatutMarital":"Celibataire","StatutOccupation":"Propriétaire du sol et du logement","StatutMaritalFreq":0.4454,"AgeMin":14,"AgeMax":19,"Alcool":162855.1911,"Tabac":98468.2848},{"Comas":"Hitiaa","Ile":"Tahiti","TrancheAge":"14 - 19 ans","Sexe":"Homme","StatutMarital":"Celibataire","StatutOccupation":"Propriétaire du sol et du logement","StatutMaritalFreq":0.5546,"AgeMin":14,"AgeMax":19,"Alcool":162855.1911,"Tabac":98468.2848},{"Comas":"Hitiaa","Ile":"Tahiti","TrancheAge":"20 - 29 ans","Sexe":"Femme","StatutMarital":"Celibataire","StatutOccupation":"Propriétaire du sol et du logement","StatutMaritalFreq":0.4851,"AgeMin":20,"AgeMax":29,"Alcool":162855.1911,"Tabac":98468.2848},{"Comas":"Hitiaa","Ile":"Tahiti","TrancheAge":"20 - 29 ans","Sexe":"Homme","StatutMarital":"Celibataire","StatutOccupation":"Propriétaire du sol et du logement","StatutMaritalFreq":0.5149,"AgeMin":20,"AgeMax":29,"Alcool":70161.7606,"Tabac":98468.2848},{"Comas":"Hitiaa","Ile":"Tahiti","TrancheAge":"30 - 39 ans","Sexe":"Femme","StatutMarital":"Celibataire","StatutOccupation":"Propriétaire du sol et du logement","StatutMaritalFreq":0.478,"AgeMin":30,"AgeMax":39,"Alcool":162855.1911,"Tabac":98468.2848},{"Comas":"Hitiaa","Ile":"Tahiti","TrancheAge":"30 - 39 ans","Sexe":"Homme","StatutMarital":"Celibataire","StatutOccupation":"Propriétaire du sol et du logement","StatutMaritalFreq":0.522,"AgeMin":30,"AgeMax":39,"Alcool":72699.189,"Tabac":30763.6087},{"Comas":"Hitiaa","Ile":"Tahiti","TrancheAge":"40 - 49 ans","Sexe":"Femme","StatutMarital":"Marie","StatutOccupation":"Propriétaire du sol et du logement","StatutMaritalFreq":0.5115,"AgeMin":40,"AgeMax":49,"Alcool":162855.1911,"Tabac":62521.1753},{"Comas":"Hitiaa","Ile":"Tahiti","TrancheAge":"40 - 49 ans","Sexe":"Homme","StatutMarital":"Marie","StatutOccupation":"Propriétaire du sol et du logement","StatutMaritalFreq":0.4885,"AgeMin":40,"AgeMax":49,"Alcool":162855.1911,"Tabac":98468.2848},{"Comas":"Hitiaa","Ile":"Tahiti","TrancheAge":"50 - 59 ans","Sexe":"Femme","StatutMarital":"Marie","StatutOccupation":"Propriétaire du sol et du logement","StatutMaritalFreq":0.427,"AgeMin":50,"AgeMax":59,"Alcool":162855.1911,"Tabac":98468.2848},{"Comas":"Hitiaa","Ile":"Tahiti","TrancheAge":"50 - 59 ans","Sexe":"Homme","StatutMarital":"Marie","StatutOccupation":"Propriétaire du sol et du logement","StatutMaritalFreq":0.573,"AgeMin":50,"AgeMax":59,"Alcool":70551.0452,"Tabac":98468.2848},{"Comas":"Hitiaa","Ile":"Tahiti","TrancheAge":"60 ans +","Sexe":"Femme","StatutMarital":"Marie","StatutOccupation":"Propriétaire du sol et du logement","StatutMaritalFreq":0.5608,"AgeMin":60,"AgeMax":150,"Alcool":70545.6386,"Tabac":58210.1708},{"Comas":"Hitiaa","Ile":"Tahiti","TrancheAge":"60 ans +","Sexe":"Homme","StatutMarital":"Marie","StatutOccupation":"Propriétaire du sol et du logement","StatutMaritalFreq":0.4392,"AgeMin":60,"AgeMax":150,"Alcool":20862.2638,"Tabac":25475.2281},{"Comas":"Hitiaa","Ile":"Tahiti","Sexe":"Femme","StatutMarital":"Marie","StatutOccupation":"Propriétaire du sol et du logement","StatutMaritalFreq":1,"AgeMax":150,"Alcool":162855.1911,"Tabac":98468.2848},{"Comas":"Mahaena","Ile":"Tahiti","TrancheAge":"0 - 13 ans","Sexe":"Femme","StatutMarital":"Non concerne","StatutOccupation":"Propriétaire du sol et du logement","StatutMaritalFreq":0.5036,"AgeMin":0,"AgeMax":13,"Alcool":162855.1911,"Tabac":98468.2848},{"Comas":"Mahaena","Ile":"Tahiti","TrancheAge":"0 - 13 ans","Sexe":"Homme","StatutMarital":"Non concerne","StatutOccupation":"Propriétaire du sol et du logement","StatutMaritalFreq":0.4964,"AgeMin":0,"AgeMax":13,"Alcool":162855.1911,"Tabac":98468.2848},{"Comas":"Mahaena","Ile":"Tahiti","TrancheAge":"14 - 19 ans","Sexe":"Femme","StatutMarital":"Celibataire","StatutOccupation":"Propriétaire du sol et du logement","StatutMaritalFreq":0.406,"AgeMin":14,"AgeMax":19,"Alcool":162855.1911,"Tabac":98468.2848},{"Comas":"Mahaena","Ile":"Tahiti","TrancheAge":"14 - 19 ans","Sexe":"Homme","StatutMarital":"Celibataire","StatutOccupation":"Propriétaire du sol et du logement","StatutMaritalFreq":0.594,"AgeMin":14,"AgeMax":19,"Alcool":162855.1911,"Tabac":98468.2848},{"Comas":"Mahaena","Ile":"Tahiti","TrancheAge":"20 - 29 ans","Sexe":"Femme","StatutMarital":"Celibataire","StatutOccupation":"Propriétaire du sol et du logement","StatutMaritalFreq":0.4889,"AgeMin":20,"AgeMax":29,"Alcool":162855.1911,"Tabac":98468.2848},{"Comas":"Mahaena","Ile":"Tahiti","TrancheAge":"20 - 29 ans","Sexe":"Homme","StatutMarital":"Celibataire","StatutOccupation":"Propriétaire du sol et du logement","StatutMaritalFreq":0.5111,"AgeMin":20,"AgeMax":29,"Alcool":162855.1911,"Tabac":98468.2848},{"Comas":"Mahaena","Ile":"Tahiti","TrancheAge":"30 - 39 ans","Sexe":"Femme","StatutMarital":"Celibataire","StatutOccupation":"Propriétaire du sol et du logement","StatutMaritalFreq":0.4746,"AgeMin":30,"AgeMax":39,"Alcool":7267.3937,"Tabac":18313.837},{"Comas":"Mahaena","Ile":"Tahiti","TrancheAge":"30 - 39 ans","Sexe":"Homme","StatutMarital":"Celibataire","StatutOccupation":"Propriétaire du sol et du logement","StatutMaritalFreq":0.5254,"AgeMin":30,"AgeMax":39,"Alcool":162855.1911,"Tabac":98468.2848},{"Comas":"Mahaena","Ile":"Tahiti","TrancheAge":"40 - 49 ans","Sexe":"Femme","StatutMarital":"Marie","StatutOccupation":"Propriétaire du sol et du logement","StatutMaritalFreq":0.4744,"AgeMin":40,"AgeMax":49,"Alcool":162855.1911,"Tabac":19124.8183},{"Comas":"Mahaena","Ile":"Tahiti","TrancheAge":"40 - 49 ans","Sexe":"Homme","StatutMarital":"Marie","StatutOccupation":"Propriétaire du sol et du logement","StatutMaritalFreq":0.5256,"AgeMin":40,"AgeMax":49,"Alcool":7240.2486,"Tabac":18245.4313},{"Comas":"Mahaena","Ile":"Tahiti","TrancheAge":"50 - 59 ans","Sexe":"Femme","StatutMarital":"Marie","StatutOccupation":"Propriétaire du sol et du logement","StatutMaritalFreq":0.42,"AgeMin":50,"AgeMax":59,"Alcool":162855.1911,"Tabac":98468.2848},{"Comas":"Mahaena","Ile":"Tahiti","TrancheAge":"50 - 59 ans","Sexe":"Homme","StatutMarital":"Marie","StatutOccupation":"Propriétaire du sol et du logement","StatutMaritalFreq":0.58,"AgeMin":50,"AgeMax":59,"Alcool":162855.1911,"Tabac":98468.2848},{"Comas":"Mahaena","Ile":"Tahiti","TrancheAge":"60 ans +","Sexe":"Femme","StatutMarital":"Veuf,veuve","StatutOccupation":"Propriétaire du sol et du logement","StatutMaritalFreq":0.5412,"AgeMin":60,"AgeMax":150,"Alcool":162855.1911,"Tabac":98468.2848},{"Comas":"Mahaena","Ile":"Tahiti","TrancheAge":"60 ans +","Sexe":"Homme","StatutMarital":"Marie","StatutOccupation":"Propriétaire du sol et du logement","StatutMaritalFreq":0.4588,"AgeMin":60,"AgeMax":150,"Alcool":162855.1911,"Tabac":15554.7962},{"Comas":"Mahina","Ile":"Tahiti","TrancheAge":"0 - 13 ans","Sexe":"Femme","StatutMarital":"Non concerne","StatutOccupation":"Propriétaire du sol et du logement","StatutMaritalFreq":0.493,"AgeMin":0,"AgeMax":13,"Alcool":162855.1911,"Tabac":98468.2848},{"Comas":"Mahina","Ile":"Tahiti","TrancheAge":"0 - 13 ans","Sexe":"Homme","StatutMarital":"Non concerne","StatutOccupation":"Propriétaire du sol et du logement","StatutMaritalFreq":0.507,"AgeMin":0,"AgeMax":13,"Alcool":162855.1911,"Tabac":98468.2848},{"Comas":"Mahina","Ile":"Tahiti","TrancheAge":"14 - 19 ans","Sexe":"Femme","StatutMarital":"Celibataire","StatutOccupation":"Propriétaire du sol et du logement","StatutMaritalFreq":0.4925,"AgeMin":14,"AgeMax":19,"Alcool":162855.1911,"Tabac":98468.2848},{"Comas":"Mahina","Ile":"Tahiti","TrancheAge":"14 - 19 ans","Sexe":"Homme","StatutMarital":"Celibataire","StatutOccupation":"Propriétaire du sol et du logement","StatutMaritalFreq":0.5075,"AgeMin":14,"AgeMax":19,"Alcool":162855.1911,"Tabac":98468.2848},{"Comas":"Mahina","Ile":"Tahiti","TrancheAge":"20 - 29 ans","Sexe":"Femme","StatutMarital":"Celibataire","StatutOccupation":"Propriétaire du sol et du logement","StatutMaritalFreq":0.508,"AgeMin":20,"AgeMax":29,"Alcool":603697.8974,"Tabac":98468.2848},{"Comas":"Mahina","Ile":"Tahiti","TrancheAge":"20 - 29 ans","Sexe":"Homme","StatutMarital":"Celibataire","StatutOccupation":"Propriétaire du sol et du logement","StatutMaritalFreq":0.492,"AgeMin":20,"AgeMax":29,"Alcool":313816.337,"Tabac":229106.3224},{"Comas":"Mahina","Ile":"Tahiti","TrancheAge":"30 - 39 ans","Sexe":"Femme","StatutMarital":"Celibataire","StatutOccupation":"Propriétaire du sol et du logement","StatutMaritalFreq":0.5151,"AgeMin":30,"AgeMax":39,"Alcool":186664.1862,"Tabac":162071.0943},{"Comas":"Mahina","Ile":"Tahiti","TrancheAge":"30 - 39 ans","Sexe":"Homme","StatutMarital":"Celibataire","StatutOccupation":"Propriétaire du sol et du logement","StatutMaritalFreq":0.4849,"AgeMin":30,"AgeMax":39,"Alcool":142501.2773,"Tabac":125987.2185},{"Comas":"Mahina","Ile":"Tahiti","TrancheAge":"40 - 49 ans","Sexe":"Femme","StatutMarital":"Marie","StatutOccupation":"Propriétaire du sol et du logement","StatutMaritalFreq":0.4867,"AgeMin":40,"AgeMax":49,"Alcool":244127.6553,"Tabac":178229.0554},{"Comas":"Mahina","Ile":"Tahiti","TrancheAge":"40 - 49 ans","Sexe":"Homme","StatutMarital":"Celibataire","StatutOccupation":"Propriétaire du sol et du logement","StatutMaritalFreq":0.5133,"AgeMin":40,"AgeMax":49,"Alcool":46103.4014,"Tabac":77392.2683},{"Comas":"Mahina","Ile":"Tahiti","TrancheAge":"50 - 59 ans","Sexe":"Femme","StatutMarital":"Marie","StatutOccupation":"Propriétaire du sol et du logement","StatutMaritalFreq":0.4895,"AgeMin":50,"AgeMax":59,"Alcool":157831.359,"Tabac":80236.9082},{"Comas":"Mahina","Ile":"Tahiti","TrancheAge":"50 - 59 ans","Sexe":"Homme","StatutMarital":"Marie","StatutOccupation":"Propriétaire du sol et du logement","StatutMaritalFreq":0.5105,"AgeMin":50,"AgeMax":59,"Alcool":79160.1885,"Tabac":72766.8303},{"Comas":"Mahina","Ile":"Tahiti","TrancheAge":"60 ans +","Sexe":"Femme","StatutMarital":"Marie","StatutOccupation":"Propriétaire du sol et du logement","StatutMaritalFreq":0.5188,"AgeMin":60,"AgeMax":150,"Alcool":80478.7147,"Tabac":72005.389},{"Comas":"Mahina","Ile":"Tahiti","TrancheAge":"60 ans +","Sexe":"Homme","StatutMarital":"Marie","StatutOccupation":"Propriétaire du sol et du logement","StatutMaritalFreq":0.4812,"AgeMin":60,"AgeMax":150,"Alcool":87604.6302,"Tabac":60314.9411},{"Comas":"Mahina","Ile":"Tahiti","Sexe":"Femme","StatutMarital":"Veuf,veuve","StatutOccupation":"Propriétaire du sol et du logement","StatutMaritalFreq":1,"AgeMax":150,"Alcool":162855.1911,"Tabac":98468.2848},{"Comas":"Mataiea","Ile":"Tahiti","TrancheAge":"0 - 13 ans","Sexe":"Femme","StatutMarital":"Non concerne","StatutOccupation":"Propriétaire du sol et du logement","StatutMaritalFreq":0.4674,"AgeMin":0,"AgeMax":13,"Alcool":162855.1911,"Tabac":98468.2848},{"Comas":"Mataiea","Ile":"Tahiti","TrancheAge":"0 - 13 ans","Sexe":"Homme","StatutMarital":"Non concerne","StatutOccupation":"Propriétaire du sol et du logement","StatutMaritalFreq":0.5326,"AgeMin":0,"AgeMax":13,"Alcool":162855.1911,"Tabac":98468.2848},{"Comas":"Mataiea","Ile":"Tahiti","TrancheAge":"14 - 19 ans","Sexe":"Femme","StatutMarital":"Celibataire","StatutOccupation":"Propriétaire du sol et du logement","StatutMaritalFreq":0.5127,"AgeMin":14,"AgeMax":19,"Alcool":162855.1911,"Tabac":194096.0222},{"Comas":"Mataiea","Ile":"Tahiti","TrancheAge":"14 - 19 ans","Sexe":"Homme","StatutMarital":"Celibataire","StatutOccupation":"Propriétaire du sol et du logement","StatutMaritalFreq":0.4873,"AgeMin":14,"AgeMax":19,"Alcool":162855.1911,"Tabac":98468.2848},{"Comas":"Mataiea","Ile":"Tahiti","TrancheAge":"20 - 29 ans","Sexe":"Femme","StatutMarital":"Celibataire","StatutOccupation":"Propriétaire du sol et du logement","StatutMaritalFreq":0.4869,"AgeMin":20,"AgeMax":29,"Alcool":162855.1911,"Tabac":162073.5187},{"Comas":"Mataiea","Ile":"Tahiti","TrancheAge":"20 - 29 ans","Sexe":"Homme","StatutMarital":"Celibataire","StatutOccupation":"Propriétaire du sol et du logement","StatutMaritalFreq":0.5131,"AgeMin":20,"AgeMax":29,"Alcool":181903.9367,"Tabac":260749.5574},{"Comas":"Mataiea","Ile":"Tahiti","TrancheAge":"30 - 39 ans","Sexe":"Femme","StatutMarital":"Celibataire","StatutOccupation":"Propriétaire du sol et du logement","StatutMaritalFreq":0.5,"AgeMin":30,"AgeMax":39,"Alcool":112435.1221,"Tabac":88854.841},{"Comas":"Mataiea","Ile":"Tahiti","TrancheAge":"30 - 39 ans","Sexe":"Homme","StatutMarital":"Celibataire","StatutOccupation":"Propriétaire du sol et du logement","StatutMaritalFreq":0.5,"AgeMin":30,"AgeMax":39,"Alcool":107216.357,"Tabac":98060.1524},{"Comas":"Mataiea","Ile":"Tahiti","TrancheAge":"40 - 49 ans","Sexe":"Femme","StatutMarital":"Marie","StatutOccupation":"Propriétaire du sol et du logement","StatutMaritalFreq":0.5086,"AgeMin":40,"AgeMax":49,"Alcool":43183.9422,"Tabac":60091.2272},{"Comas":"Mataiea","Ile":"Tahiti","TrancheAge":"40 - 49 ans","Sexe":"Homme","StatutMarital":"Celibataire","StatutOccupation":"Propriétaire du sol et du logement","StatutMaritalFreq":0.4914,"AgeMin":40,"AgeMax":49,"Alcool":51128.142,"Tabac":146176.4513},{"Comas":"Mataiea","Ile":"Tahiti","TrancheAge":"50 - 59 ans","Sexe":"Femme","StatutMarital":"Marie","StatutOccupation":"Propriétaire du sol et du logement","StatutMaritalFreq":0.4645,"AgeMin":50,"AgeMax":59,"Alcool":162855.1911,"Tabac":210042.6163},{"Comas":"Mataiea","Ile":"Tahiti","TrancheAge":"50 - 59 ans","Sexe":"Homme","StatutMarital":"Marie","StatutOccupation":"Propriétaire du sol et du logement","StatutMaritalFreq":0.5355,"AgeMin":50,"AgeMax":59,"Alcool":31272.1212,"Tabac":39762.962},{"Comas":"Mataiea","Ile":"Tahiti","TrancheAge":"60 ans +","Sexe":"Femme","StatutMarital":"Marie","StatutOccupation":"Propriétaire du sol et du logement","StatutMaritalFreq":0.4887,"AgeMin":60,"AgeMax":150,"Alcool":92924.8088,"Tabac":80421.9867},{"Comas":"Mataiea","Ile":"Tahiti","TrancheAge":"60 ans +","Sexe":"Homme","StatutMarital":"Marie","StatutOccupation":"Propriétaire du sol et du logement","StatutMaritalFreq":0.5113,"AgeMin":60,"AgeMax":150,"Alcool":55216.0174,"Tabac":55612.7964},{"Comas":"Paea","Ile":"Tahiti","TrancheAge":"0 - 13 ans","Sexe":"Femme","StatutMarital":"Non concerne","StatutOccupation":"Propriétaire du sol et du logement","StatutMaritalFreq":0.4766,"AgeMin":0,"AgeMax":13,"Alcool":162855.1911,"Tabac":98468.2848},{"Comas":"Paea","Ile":"Tahiti","TrancheAge":"0 - 13 ans","Sexe":"Homme","StatutMarital":"Non concerne","StatutOccupation":"Propriétaire du sol et du logement","StatutMaritalFreq":0.5234,"AgeMin":0,"AgeMax":13,"Alcool":162855.1911,"Tabac":98468.2848},{"Comas":"Paea","Ile":"Tahiti","TrancheAge":"14 - 19 ans","Sexe":"Femme","StatutMarital":"Celibataire","StatutOccupation":"Propriétaire du sol et du logement","StatutMaritalFreq":0.4967,"AgeMin":14,"AgeMax":19,"Alcool":162855.1911,"Tabac":98468.2848},{"Comas":"Paea","Ile":"Tahiti","TrancheAge":"14 - 19 ans","Sexe":"Homme","StatutMarital":"Celibataire","StatutOccupation":"Propriétaire du sol et du logement","StatutMaritalFreq":0.5033,"AgeMin":14,"AgeMax":19,"Alcool":162855.1911,"Tabac":98468.2848},{"Comas":"Paea","Ile":"Tahiti","TrancheAge":"20 - 29 ans","Sexe":"Femme","StatutMarital":"Celibataire","StatutOccupation":"Propriétaire du sol et du logement","StatutMaritalFreq":0.5073,"AgeMin":20,"AgeMax":29,"Alcool":307863.649,"Tabac":108640.8962},{"Comas":"Paea","Ile":"Tahiti","TrancheAge":"20 - 29 ans","Sexe":"Homme","StatutMarital":"Celibataire","StatutOccupation":"Propriétaire du sol et du logement","StatutMaritalFreq":0.4927,"AgeMin":20,"AgeMax":29,"Alcool":259852.6324,"Tabac":98468.2848},{"Comas":"Paea","Ile":"Tahiti","TrancheAge":"30 - 39 ans","Sexe":"Femme","StatutMarital":"Celibataire","StatutOccupation":"Propriétaire du sol et du logement","StatutMaritalFreq":0.4945,"AgeMin":30,"AgeMax":39,"Alcool":165576.2671,"Tabac":94877.3463},{"Comas":"Paea","Ile":"Tahiti","TrancheAge":"30 - 39 ans","Sexe":"Homme","StatutMarital":"Celibataire","StatutOccupation":"Propriétaire du sol et du logement","StatutMaritalFreq":0.5055,"AgeMin":30,"AgeMax":39,"Alcool":95476.554,"Tabac":105583.9182},{"Comas":"Paea","Ile":"Tahiti","TrancheAge":"40 - 49 ans","Sexe":"Femme","StatutMarital":"Marie","StatutOccupation":"Propriétaire du sol et du logement","StatutMaritalFreq":0.4906,"AgeMin":40,"AgeMax":49,"Alcool":349795.2816,"Tabac":169311.5854},{"Comas":"Paea","Ile":"Tahiti","TrancheAge":"40 - 49 ans","Sexe":"Homme","StatutMarital":"Celibataire","StatutOccupation":"Propriétaire du sol et du logement","StatutMaritalFreq":0.5094,"AgeMin":40,"AgeMax":49,"Alcool":46842.9896,"Tabac":39230.7692},{"Comas":"Paea","Ile":"Tahiti","TrancheAge":"50 - 59 ans","Sexe":"Femme","StatutMarital":"Marie","StatutOccupation":"Propriétaire du sol et du logement","StatutMaritalFreq":0.4706,"AgeMin":50,"AgeMax":59,"Alcool":75942.7238,"Tabac":46372.6702},{"Comas":"Paea","Ile":"Tahiti","TrancheAge":"50 - 59 ans","Sexe":"Homme","StatutMarital":"Marie","StatutOccupation":"Propriétaire du sol et du logement","StatutMaritalFreq":0.5294,"AgeMin":50,"AgeMax":59,"Alcool":52081.5404,"Tabac":45369.0717},{"Comas":"Paea","Ile":"Tahiti","TrancheAge":"60 ans +","Sexe":"Femme","StatutMarital":"Marie","StatutOccupation":"Propriétaire du sol et du logement","StatutMaritalFreq":0.5117,"AgeMin":60,"AgeMax":150,"Alcool":276783.1138,"Tabac":83201.6853},{"Comas":"Paea","Ile":"Tahiti","TrancheAge":"60 ans +","Sexe":"Homme","StatutMarital":"Marie","StatutOccupation":"Propriétaire du sol et du logement","StatutMaritalFreq":0.4883,"AgeMin":60,"AgeMax":150,"Alcool":114474.8624,"Tabac":64998.3569},{"Comas":"Paea","Ile":"Tahiti","Sexe":"Femme","StatutMarital":"Veuf,veuve","StatutOccupation":"Propriétaire du sol et du logement","StatutMaritalFreq":1,"AgeMax":150,"Alcool":162855.1911,"Tabac":98468.2848},{"Comas":"Papara","Ile":"Tahiti","TrancheAge":"0 - 13 ans","Sexe":"Femme","StatutMarital":"Non concerne","StatutOccupation":"Propriétaire du sol et du logement","StatutMaritalFreq":0.488,"AgeMin":0,"AgeMax":13,"Alcool":162855.1911,"Tabac":98468.2848},{"Comas":"Papara","Ile":"Tahiti","TrancheAge":"0 - 13 ans","Sexe":"Homme","StatutMarital":"Non concerne","StatutOccupation":"Propriétaire du sol et du logement","StatutMaritalFreq":0.512,"AgeMin":0,"AgeMax":13,"Alcool":162855.1911,"Tabac":98468.2848},{"Comas":"Papara","Ile":"Tahiti","TrancheAge":"14 - 19 ans","Sexe":"Femme","StatutMarital":"Celibataire","StatutOccupation":"Propriétaire du sol et du logement","StatutMaritalFreq":0.4984,"AgeMin":14,"AgeMax":19,"Alcool":162855.1911,"Tabac":98468.2848},{"Comas":"Papara","Ile":"Tahiti","TrancheAge":"14 - 19 ans","Sexe":"Homme","StatutMarital":"Celibataire","StatutOccupation":"Propriétaire du sol et du logement","StatutMaritalFreq":0.5016,"AgeMin":14,"AgeMax":19,"Alcool":162855.1911,"Tabac":98468.2848},{"Comas":"Papara","Ile":"Tahiti","TrancheAge":"20 - 29 ans","Sexe":"Femme","StatutMarital":"Celibataire","StatutOccupation":"Propriétaire du sol et du logement","StatutMaritalFreq":0.4896,"AgeMin":20,"AgeMax":29,"Alcool":771165.3344,"Tabac":84502.1234},{"Comas":"Papara","Ile":"Tahiti","TrancheAge":"20 - 29 ans","Sexe":"Homme","StatutMarital":"Celibataire","StatutOccupation":"Propriétaire du sol et du logement","StatutMaritalFreq":0.5104,"AgeMin":20,"AgeMax":29,"Alcool":271076.3732,"Tabac":365310.2002},{"Comas":"Papara","Ile":"Tahiti","TrancheAge":"30 - 39 ans","Sexe":"Femme","StatutMarital":"Celibataire","StatutOccupation":"Propriétaire du sol et du logement","StatutMaritalFreq":0.5086,"AgeMin":30,"AgeMax":39,"Alcool":844865.4486,"Tabac":110190.3341},{"Comas":"Papara","Ile":"Tahiti","TrancheAge":"30 - 39 ans","Sexe":"Homme","StatutMarital":"Celibataire","StatutOccupation":"Propriétaire du sol et du logement","StatutMaritalFreq":0.4914,"AgeMin":30,"AgeMax":39,"Alcool":93709.7279,"Tabac":113680.4287},{"Comas":"Papara","Ile":"Tahiti","TrancheAge":"40 - 49 ans","Sexe":"Femme","StatutMarital":"Marie","StatutOccupation":"Propriétaire du sol et du logement","StatutMaritalFreq":0.4894,"AgeMin":40,"AgeMax":49,"Alcool":174513.3669,"Tabac":78064.469},{"Comas":"Papara","Ile":"Tahiti","TrancheAge":"40 - 49 ans","Sexe":"Homme","StatutMarital":"Celibataire","StatutOccupation":"Propriétaire du sol et du logement","StatutMaritalFreq":0.5106,"AgeMin":40,"AgeMax":49,"Alcool":94108.2451,"Tabac":40849.1117},{"Comas":"Papara","Ile":"Tahiti","TrancheAge":"50 - 59 ans","Sexe":"Femme","StatutMarital":"Marie","StatutOccupation":"Propriétaire du sol et du logement","StatutMaritalFreq":0.4636,"AgeMin":50,"AgeMax":59,"Alcool":141252.587,"Tabac":40155.5556},{"Comas":"Papara","Ile":"Tahiti","TrancheAge":"50 - 59 ans","Sexe":"Homme","StatutMarital":"Marie","StatutOccupation":"Propriétaire du sol et du logement","StatutMaritalFreq":0.5364,"AgeMin":50,"AgeMax":59,"Alcool":61079.1407,"Tabac":34068.8277},{"Comas":"Papara","Ile":"Tahiti","TrancheAge":"60 ans +","Sexe":"Femme","StatutMarital":"Marie","StatutOccupation":"Propriétaire du sol et du logement","StatutMaritalFreq":0.4897,"AgeMin":60,"AgeMax":150,"Alcool":390746.5659,"Tabac":156749.0881},{"Comas":"Papara","Ile":"Tahiti","TrancheAge":"60 ans +","Sexe":"Homme","StatutMarital":"Marie","StatutOccupation":"Propriétaire du sol et du logement","StatutMaritalFreq":0.5103,"AgeMin":60,"AgeMax":150,"Alcool":83852.9752,"Tabac":104931.8151},{"Comas":"Papara","Ile":"Tahiti","Sexe":"Femme","StatutMarital":"Veuf,veuve","StatutOccupation":"Propriétaire du sol et du logement","StatutMaritalFreq":1,"AgeMax":150,"Alcool":162855.1911,"Tabac":98468.2848},{"Comas":"Papeari","Ile":"Tahiti","TrancheAge":"0 - 13 ans","Sexe":"Femme","StatutMarital":"Non concerne","StatutOccupation":"Propriétaire du sol et du logement","StatutMaritalFreq":0.4763,"AgeMin":0,"AgeMax":13,"Alcool":162855.1911,"Tabac":98468.2848},{"Comas":"Papeari","Ile":"Tahiti","TrancheAge":"0 - 13 ans","Sexe":"Homme","StatutMarital":"Non concerne","StatutOccupation":"Propriétaire du sol et du logement","StatutMaritalFreq":0.5237,"AgeMin":0,"AgeMax":13,"Alcool":162855.1911,"Tabac":98468.2848},{"Comas":"Papeari","Ile":"Tahiti","TrancheAge":"14 - 19 ans","Sexe":"Femme","StatutMarital":"Celibataire","StatutOccupation":"Propriétaire du sol et du logement","StatutMaritalFreq":0.478,"AgeMin":14,"AgeMax":19,"Alcool":162855.1911,"Tabac":98468.2848},{"Comas":"Papeari","Ile":"Tahiti","TrancheAge":"14 - 19 ans","Sexe":"Homme","StatutMarital":"Celibataire","StatutOccupation":"Propriétaire du sol et du logement","StatutMaritalFreq":0.522,"AgeMin":14,"AgeMax":19,"Alcool":162855.1911,"Tabac":98468.2848},{"Comas":"Papeari","Ile":"Tahiti","TrancheAge":"20 - 29 ans","Sexe":"Femme","StatutMarital":"Celibataire","StatutOccupation":"Propriétaire du sol et du logement","StatutMaritalFreq":0.496,"AgeMin":20,"AgeMax":29,"Alcool":162855.1911,"Tabac":109311.5976},{"Comas":"Papeari","Ile":"Tahiti","TrancheAge":"20 - 29 ans","Sexe":"Homme","StatutMarital":"Celibataire","StatutOccupation":"Propriétaire du sol et du logement","StatutMaritalFreq":0.504,"AgeMin":20,"AgeMax":29,"Alcool":162855.1911,"Tabac":98468.2848},{"Comas":"Papeari","Ile":"Tahiti","TrancheAge":"30 - 39 ans","Sexe":"Femme","StatutMarital":"Celibataire","StatutOccupation":"Propriétaire du sol et du logement","StatutMaritalFreq":0.4792,"AgeMin":30,"AgeMax":39,"Alcool":162855.1911,"Tabac":98468.2848},{"Comas":"Papeari","Ile":"Tahiti","TrancheAge":"30 - 39 ans","Sexe":"Homme","StatutMarital":"Celibataire","StatutOccupation":"Propriétaire du sol et du logement","StatutMaritalFreq":0.5208,"AgeMin":30,"AgeMax":39,"Alcool":75054.3296,"Tabac":145814.6984},{"Comas":"Papeari","Ile":"Tahiti","TrancheAge":"40 - 49 ans","Sexe":"Femme","StatutMarital":"Marie","StatutOccupation":"Propriétaire du sol et du logement","StatutMaritalFreq":0.5029,"AgeMin":40,"AgeMax":49,"Alcool":77782.4539,"Tabac":58729.947},{"Comas":"Papeari","Ile":"Tahiti","TrancheAge":"40 - 49 ans","Sexe":"Homme","StatutMarital":"Celibataire","StatutOccupation":"Propriétaire du sol et du logement","StatutMaritalFreq":0.4971,"AgeMin":40,"AgeMax":49,"Alcool":27167.7335,"Tabac":13838.9574},{"Comas":"Papeari","Ile":"Tahiti","TrancheAge":"50 - 59 ans","Sexe":"Femme","StatutMarital":"Marie","StatutOccupation":"Propriétaire du sol et du logement","StatutMaritalFreq":0.4577,"AgeMin":50,"AgeMax":59,"Alcool":143573.1672,"Tabac":95391.504},{"Comas":"Papeari","Ile":"Tahiti","TrancheAge":"50 - 59 ans","Sexe":"Homme","StatutMarital":"Marie","StatutOccupation":"Propriétaire du sol et du logement","StatutMaritalFreq":0.5423,"AgeMin":50,"AgeMax":59,"Alcool":102166.057,"Tabac":135760.3796},{"Comas":"Papeari","Ile":"Tahiti","TrancheAge":"60 ans +","Sexe":"Femme","StatutMarital":"Marie","StatutOccupation":"Propriétaire du sol et du logement","StatutMaritalFreq":0.5113,"AgeMin":60,"AgeMax":150,"Alcool":193052.0253,"Tabac":56309.4851},{"Comas":"Papeari","Ile":"Tahiti","TrancheAge":"60 ans +","Sexe":"Homme","StatutMarital":"Marie","StatutOccupation":"Propriétaire du sol et du logement","StatutMaritalFreq":0.4887,"AgeMin":60,"AgeMax":150,"Alcool":41755.5626,"Tabac":27192.5123},{"Comas":"Papeete","Ile":"Tahiti","TrancheAge":"0 - 13 ans","Sexe":"Femme","StatutMarital":"Non concerne","StatutOccupation":"Propriétaire du sol et du logement","StatutMaritalFreq":0.4751,"AgeMin":0,"AgeMax":13,"Alcool":162855.1911,"Tabac":98468.2848},{"Comas":"Papeete","Ile":"Tahiti","TrancheAge":"0 - 13 ans","Sexe":"Homme","StatutMarital":"Non concerne","StatutOccupation":"Propriétaire du sol et du logement","StatutMaritalFreq":0.5249,"AgeMin":0,"AgeMax":13,"Alcool":162855.1911,"Tabac":98468.2848},{"Comas":"Papeete","Ile":"Tahiti","TrancheAge":"14 - 19 ans","Sexe":"Femme","StatutMarital":"Celibataire","StatutOccupation":"Propriétaire du sol et du logement","StatutMaritalFreq":0.5002,"AgeMin":14,"AgeMax":19,"Alcool":162855.1911,"Tabac":98468.2848},{"Comas":"Papeete","Ile":"Tahiti","TrancheAge":"14 - 19 ans","Sexe":"Homme","StatutMarital":"Celibataire","StatutOccupation":"Propriétaire du sol et du logement","StatutMaritalFreq":0.4998,"AgeMin":14,"AgeMax":19,"Alcool":162855.1911,"Tabac":98468.2848},{"Comas":"Papeete","Ile":"Tahiti","TrancheAge":"20 - 29 ans","Sexe":"Femme","StatutMarital":"Celibataire","StatutOccupation":"Propriétaire du sol et du logement","StatutMaritalFreq":0.5056,"AgeMin":20,"AgeMax":29,"Alcool":1081213.8153,"Tabac":479495.6572},{"Comas":"Papeete","Ile":"Tahiti","TrancheAge":"20 - 29 ans","Sexe":"Homme","StatutMarital":"Celibataire","StatutOccupation":"Propriétaire du sol et du logement","StatutMaritalFreq":0.4944,"AgeMin":20,"AgeMax":29,"Alcool":141953.6656,"Tabac":148971.2288},{"Comas":"Papeete","Ile":"Tahiti","TrancheAge":"30 - 39 ans","Sexe":"Femme","StatutMarital":"Celibataire","StatutOccupation":"Propriétaire du sol et du logement","StatutMaritalFreq":0.4859,"AgeMin":30,"AgeMax":39,"Alcool":482091.6683,"Tabac":532043.1264},{"Comas":"Papeete","Ile":"Tahiti","TrancheAge":"30 - 39 ans","Sexe":"Homme","StatutMarital":"Celibataire","StatutOccupation":"Propriétaire du sol et du logement","StatutMaritalFreq":0.5141,"AgeMin":30,"AgeMax":39,"Alcool":66655.9717,"Tabac":43195.1148},{"Comas":"Papeete","Ile":"Tahiti","TrancheAge":"40 - 49 ans","Sexe":"Femme","StatutMarital":"Marie","StatutOccupation":"Propriétaire du sol et du logement","StatutMaritalFreq":0.4967,"AgeMin":40,"AgeMax":49,"Alcool":346546.3778,"Tabac":86055.3346},{"Comas":"Papeete","Ile":"Tahiti","TrancheAge":"40 - 49 ans","Sexe":"Homme","StatutMarital":"Celibataire","StatutOccupation":"Propriétaire du sol et du logement","StatutMaritalFreq":0.5033,"AgeMin":40,"AgeMax":49,"Alcool":55877.0729,"Tabac":63397.3684},{"Comas":"Papeete","Ile":"Tahiti","TrancheAge":"50 - 59 ans","Sexe":"Femme","StatutMarital":"Marie","StatutOccupation":"Propriétaire du sol et du logement","StatutMaritalFreq":0.5026,"AgeMin":50,"AgeMax":59,"Alcool":149943.6531,"Tabac":79029.5961},{"Comas":"Papeete","Ile":"Tahiti","TrancheAge":"50 - 59 ans","Sexe":"Homme","StatutMarital":"Marie","StatutOccupation":"Propriétaire du sol et du logement","StatutMaritalFreq":0.4974,"AgeMin":50,"AgeMax":59,"Alcool":55412.1661,"Tabac":27628.1394},{"Comas":"Papeete","Ile":"Tahiti","TrancheAge":"60 ans +","Sexe":"Femme","StatutMarital":"Marie","StatutOccupation":"Propriétaire du sol et du logement","StatutMaritalFreq":0.5296,"AgeMin":60,"AgeMax":150,"Alcool":348531.0218,"Tabac":92102.9744},{"Comas":"Papeete","Ile":"Tahiti","TrancheAge":"60 ans +","Sexe":"Homme","StatutMarital":"Marie","StatutOccupation":"Propriétaire du sol et du logement","StatutMaritalFreq":0.4704,"AgeMin":60,"AgeMax":150,"Alcool":50816.8959,"Tabac":61568.6391},{"Comas":"Papeete","Ile":"Tahiti","Sexe":"Femme","StatutMarital":"Veuf,veuve","StatutOccupation":"Propriétaire du sol et du logement","StatutMaritalFreq":0.6,"AgeMax":150,"Alcool":162855.1911,"Tabac":98468.2848},{"Comas":"Papeete","Ile":"Tahiti","Sexe":"Homme","StatutMarital":"Veuf,veuve","StatutOccupation":"Propriétaire du sol et du logement","StatutMaritalFreq":0.4,"AgeMax":150,"Alcool":162855.1911,"Tabac":98468.2848},{"Comas":"Papenoo","Ile":"Tahiti","TrancheAge":"0 - 13 ans","Sexe":"Femme","StatutMarital":"Non concerne","StatutOccupation":"Propriétaire du sol et du logement","StatutMaritalFreq":0.4743,"AgeMin":0,"AgeMax":13,"Alcool":162855.1911,"Tabac":98468.2848},{"Comas":"Papenoo","Ile":"Tahiti","TrancheAge":"0 - 13 ans","Sexe":"Homme","StatutMarital":"Non concerne","StatutOccupation":"Propriétaire du sol et du logement","StatutMaritalFreq":0.5257,"AgeMin":0,"AgeMax":13,"Alcool":162855.1911,"Tabac":98468.2848},{"Comas":"Papenoo","Ile":"Tahiti","TrancheAge":"14 - 19 ans","Sexe":"Femme","StatutMarital":"Celibataire","StatutOccupation":"Propriétaire du sol et du logement","StatutMaritalFreq":0.4851,"AgeMin":14,"AgeMax":19,"Alcool":162855.1911,"Tabac":98468.2848},{"Comas":"Papenoo","Ile":"Tahiti","TrancheAge":"14 - 19 ans","Sexe":"Homme","StatutMarital":"Celibataire","StatutOccupation":"Propriétaire du sol et du logement","StatutMaritalFreq":0.5149,"AgeMin":14,"AgeMax":19,"Alcool":162855.1911,"Tabac":98468.2848},{"Comas":"Papenoo","Ile":"Tahiti","TrancheAge":"20 - 29 ans","Sexe":"Femme","StatutMarital":"Celibataire","StatutOccupation":"Propriétaire du sol et du logement","StatutMaritalFreq":0.4798,"AgeMin":20,"AgeMax":29,"Alcool":162855.1911,"Tabac":98468.2848},{"Comas":"Papenoo","Ile":"Tahiti","TrancheAge":"20 - 29 ans","Sexe":"Homme","StatutMarital":"Celibataire","StatutOccupation":"Propriétaire du sol et du logement","StatutMaritalFreq":0.5202,"AgeMin":20,"AgeMax":29,"Alcool":172066.1711,"Tabac":75370.8539},{"Comas":"Papenoo","Ile":"Tahiti","TrancheAge":"30 - 39 ans","Sexe":"Femme","StatutMarital":"Celibataire","StatutOccupation":"Propriétaire du sol et du logement","StatutMaritalFreq":0.5008,"AgeMin":30,"AgeMax":39,"Alcool":162855.1911,"Tabac":77645.5565},{"Comas":"Papenoo","Ile":"Tahiti","TrancheAge":"30 - 39 ans","Sexe":"Homme","StatutMarital":"Celibataire","StatutOccupation":"Propriétaire du sol et du logement","StatutMaritalFreq":0.4992,"AgeMin":30,"AgeMax":39,"Alcool":63012.2199,"Tabac":42504.2027},{"Comas":"Papenoo","Ile":"Tahiti","TrancheAge":"40 - 49 ans","Sexe":"Femme","StatutMarital":"Marie","StatutOccupation":"Propriétaire du sol et du logement","StatutMaritalFreq":0.4687,"AgeMin":40,"AgeMax":49,"Alcool":95325.1699,"Tabac":152892.9749},{"Comas":"Papenoo","Ile":"Tahiti","TrancheAge":"40 - 49 ans","Sexe":"Homme","StatutMarital":"Celibataire","StatutOccupation":"Propriétaire du sol et du logement","StatutMaritalFreq":0.5313,"AgeMin":40,"AgeMax":49,"Alcool":33971.4486,"Tabac":22448.8687},{"Comas":"Papenoo","Ile":"Tahiti","TrancheAge":"50 - 59 ans","Sexe":"Femme","StatutMarital":"Marie","StatutOccupation":"Propriétaire du sol et du logement","StatutMaritalFreq":0.4975,"AgeMin":50,"AgeMax":59,"Alcool":88143.8794,"Tabac":157492.256},{"Comas":"Papenoo","Ile":"Tahiti","TrancheAge":"50 - 59 ans","Sexe":"Homme","StatutMarital":"Marie","StatutOccupation":"Propriétaire du sol et du logement","StatutMaritalFreq":0.5025,"AgeMin":50,"AgeMax":59,"Alcool":82112.4306,"Tabac":144954.1061},{"Comas":"Papenoo","Ile":"Tahiti","TrancheAge":"60 ans +","Sexe":"Femme","StatutMarital":"Veuf,veuve","StatutOccupation":"Propriétaire du sol et du logement","StatutMaritalFreq":0.4676,"AgeMin":60,"AgeMax":150,"Alcool":183269.569,"Tabac":98468.2848},{"Comas":"Papenoo","Ile":"Tahiti","TrancheAge":"60 ans +","Sexe":"Homme","StatutMarital":"Marie","StatutOccupation":"Propriétaire du sol et du logement","StatutMaritalFreq":0.5324,"AgeMin":60,"AgeMax":150,"Alcool":29071.6959,"Tabac":26649.5621},{"Comas":"Pirae","Ile":"Tahiti","TrancheAge":"0 - 13 ans","Sexe":"Femme","StatutMarital":"Non concerne","StatutOccupation":"Propriétaire du sol et du logement","StatutMaritalFreq":0.4851,"AgeMin":0,"AgeMax":13,"Alcool":162855.1911,"Tabac":98468.2848},{"Comas":"Pirae","Ile":"Tahiti","TrancheAge":"0 - 13 ans","Sexe":"Homme","StatutMarital":"Non concerne","StatutOccupation":"Propriétaire du sol et du logement","StatutMaritalFreq":0.5149,"AgeMin":0,"AgeMax":13,"Alcool":162855.1911,"Tabac":98468.2848},{"Comas":"Pirae","Ile":"Tahiti","TrancheAge":"14 - 19 ans","Sexe":"Femme","StatutMarital":"Celibataire","StatutOccupation":"Propriétaire du sol et du logement","StatutMaritalFreq":0.4816,"AgeMin":14,"AgeMax":19,"Alcool":162855.1911,"Tabac":98468.2848},{"Comas":"Pirae","Ile":"Tahiti","TrancheAge":"14 - 19 ans","Sexe":"Homme","StatutMarital":"Celibataire","StatutOccupation":"Propriétaire du sol et du logement","StatutMaritalFreq":0.5184,"AgeMin":14,"AgeMax":19,"Alcool":162855.1911,"Tabac":98468.2848},{"Comas":"Pirae","Ile":"Tahiti","TrancheAge":"20 - 29 ans","Sexe":"Femme","StatutMarital":"Celibataire","StatutOccupation":"Propriétaire du sol et du logement","StatutMaritalFreq":0.4981,"AgeMin":20,"AgeMax":29,"Alcool":269818.4185,"Tabac":231118.1275},{"Comas":"Pirae","Ile":"Tahiti","TrancheAge":"20 - 29 ans","Sexe":"Homme","StatutMarital":"Celibataire","StatutOccupation":"Propriétaire du sol et du logement","StatutMaritalFreq":0.5019,"AgeMin":20,"AgeMax":29,"Alcool":171588.1074,"Tabac":109425.9254},{"Comas":"Pirae","Ile":"Tahiti","TrancheAge":"30 - 39 ans","Sexe":"Femme","StatutMarital":"Celibataire","StatutOccupation":"Propriétaire du sol et du logement","StatutMaritalFreq":0.4961,"AgeMin":30,"AgeMax":39,"Alcool":132757.183,"Tabac":221545.8421},{"Comas":"Pirae","Ile":"Tahiti","TrancheAge":"30 - 39 ans","Sexe":"Homme","StatutMarital":"Celibataire","StatutOccupation":"Propriétaire du sol et du logement","StatutMaritalFreq":0.5039,"AgeMin":30,"AgeMax":39,"Alcool":568980.7443,"Tabac":77246.3091},{"Comas":"Pirae","Ile":"Tahiti","TrancheAge":"40 - 49 ans","Sexe":"Femme","StatutMarital":"Marie","StatutOccupation":"Propriétaire du sol et du logement","StatutMaritalFreq":0.4775,"AgeMin":40,"AgeMax":49,"Alcool":156534.0042,"Tabac":74955.6016},{"Comas":"Pirae","Ile":"Tahiti","TrancheAge":"40 - 49 ans","Sexe":"Homme","StatutMarital":"Celibataire","StatutOccupation":"Propriétaire du sol et du logement","StatutMaritalFreq":0.5225,"AgeMin":40,"AgeMax":49,"Alcool":56388.3859,"Tabac":32809.4003},{"Comas":"Pirae","Ile":"Tahiti","TrancheAge":"50 - 59 ans","Sexe":"Femme","StatutMarital":"Marie","StatutOccupation":"Propriétaire du sol et du logement","StatutMaritalFreq":0.4921,"AgeMin":50,"AgeMax":59,"Alcool":530627.2275,"Tabac":234040.7138},{"Comas":"Pirae","Ile":"Tahiti","TrancheAge":"50 - 59 ans","Sexe":"Homme","StatutMarital":"Marie","StatutOccupation":"Propriétaire du sol et du logement","StatutMaritalFreq":0.5079,"AgeMin":50,"AgeMax":59,"Alcool":60331.4165,"Tabac":25560.7044},{"Comas":"Pirae","Ile":"Tahiti","TrancheAge":"60 ans +","Sexe":"Femme","StatutMarital":"Marie","StatutOccupation":"Propriétaire du sol et du logement","StatutMaritalFreq":0.5309,"AgeMin":60,"AgeMax":150,"Alcool":186067.88,"Tabac":121939.2519},{"Comas":"Pirae","Ile":"Tahiti","TrancheAge":"60 ans +","Sexe":"Homme","StatutMarital":"Marie","StatutOccupation":"Propriétaire du sol et du logement","StatutMaritalFreq":0.4691,"AgeMin":60,"AgeMax":150,"Alcool":41914.6482,"Tabac":56310.5174},{"Comas":"Pirae","Ile":"Tahiti","Sexe":"Femme","StatutMarital":"Veuf,veuve","StatutOccupation":"Propriétaire du sol et du logement","StatutMaritalFreq":1,"AgeMax":150,"Alcool":162855.1911,"Tabac":98468.2848},{"Comas":"Pueu","Ile":"Tahiti","TrancheAge":"0 - 13 ans","Sexe":"Femme","StatutMarital":"Non concerne","StatutOccupation":"Propriétaire du sol et du logement","StatutMaritalFreq":0.4701,"AgeMin":0,"AgeMax":13,"Alcool":162855.1911,"Tabac":98468.2848},{"Comas":"Pueu","Ile":"Tahiti","TrancheAge":"0 - 13 ans","Sexe":"Homme","StatutMarital":"Non concerne","StatutOccupation":"Propriétaire du sol et du logement","StatutMaritalFreq":0.5299,"AgeMin":0,"AgeMax":13,"Alcool":162855.1911,"Tabac":98468.2848},{"Comas":"Pueu","Ile":"Tahiti","TrancheAge":"14 - 19 ans","Sexe":"Femme","StatutMarital":"Celibataire","StatutOccupation":"Propriétaire du sol et du logement","StatutMaritalFreq":0.419,"AgeMin":14,"AgeMax":19,"Alcool":162855.1911,"Tabac":98468.2848},{"Comas":"Pueu","Ile":"Tahiti","TrancheAge":"14 - 19 ans","Sexe":"Homme","StatutMarital":"Celibataire","StatutOccupation":"Propriétaire du sol et du logement","StatutMaritalFreq":0.581,"AgeMin":14,"AgeMax":19,"Alcool":162855.1911,"Tabac":98468.2848},{"Comas":"Pueu","Ile":"Tahiti","TrancheAge":"20 - 29 ans","Sexe":"Femme","StatutMarital":"Celibataire","StatutOccupation":"Propriétaire du sol et du logement","StatutMaritalFreq":0.5172,"AgeMin":20,"AgeMax":29,"Alcool":12177.847,"Tabac":28232.3823},{"Comas":"Pueu","Ile":"Tahiti","TrancheAge":"20 - 29 ans","Sexe":"Homme","StatutMarital":"Celibataire","StatutOccupation":"Propriétaire du sol et du logement","StatutMaritalFreq":0.4828,"AgeMin":20,"AgeMax":29,"Alcool":162855.1911,"Tabac":98468.2848},{"Comas":"Pueu","Ile":"Tahiti","TrancheAge":"30 - 39 ans","Sexe":"Femme","StatutMarital":"Celibataire","StatutOccupation":"Propriétaire du sol et du logement","StatutMaritalFreq":0.4582,"AgeMin":30,"AgeMax":39,"Alcool":162855.1911,"Tabac":98468.2848},{"Comas":"Pueu","Ile":"Tahiti","TrancheAge":"30 - 39 ans","Sexe":"Homme","StatutMarital":"Celibataire","StatutOccupation":"Propriétaire du sol et du logement","StatutMaritalFreq":0.5418,"AgeMin":30,"AgeMax":39,"Alcool":162855.1911,"Tabac":98468.2848},{"Comas":"Pueu","Ile":"Tahiti","TrancheAge":"40 - 49 ans","Sexe":"Femme","StatutMarital":"Marie","StatutOccupation":"Propriétaire du sol et du logement","StatutMaritalFreq":0.4466,"AgeMin":40,"AgeMax":49,"Alcool":162855.1911,"Tabac":98468.2848},{"Comas":"Pueu","Ile":"Tahiti","TrancheAge":"40 - 49 ans","Sexe":"Homme","StatutMarital":"Marie","StatutOccupation":"Propriétaire du sol et du logement","StatutMaritalFreq":0.5534,"AgeMin":40,"AgeMax":49,"Alcool":162855.1911,"Tabac":25518.0564},{"Comas":"Pueu","Ile":"Tahiti","TrancheAge":"50 - 59 ans","Sexe":"Femme","StatutMarital":"Marie","StatutOccupation":"Propriétaire du sol et du logement","StatutMaritalFreq":0.4729,"AgeMin":50,"AgeMax":59,"Alcool":162855.1911,"Tabac":98468.2848},{"Comas":"Pueu","Ile":"Tahiti","TrancheAge":"50 - 59 ans","Sexe":"Homme","StatutMarital":"Marie","StatutOccupation":"Propriétaire du sol et du logement","StatutMaritalFreq":0.5271,"AgeMin":50,"AgeMax":59,"Alcool":162855.1911,"Tabac":24507.8194},{"Comas":"Pueu","Ile":"Tahiti","TrancheAge":"60 ans +","Sexe":"Femme","StatutMarital":"Marie","StatutOccupation":"Propriétaire du sol et du logement","StatutMaritalFreq":0.5549,"AgeMin":60,"AgeMax":150,"Alcool":12018.0537,"Tabac":26285.683},{"Comas":"Pueu","Ile":"Tahiti","TrancheAge":"60 ans +","Sexe":"Homme","StatutMarital":"Marie","StatutOccupation":"Propriétaire du sol et du logement","StatutMaritalFreq":0.4451,"AgeMin":60,"AgeMax":150,"Alcool":5903.6733,"Tabac":13586.8791},{"Comas":"Pueu","Ile":"Tahiti","Sexe":"Femme","StatutMarital":"Veuf,veuve","StatutOccupation":"Propriétaire du sol et du logement","StatutMaritalFreq":1,"AgeMax":150,"Alcool":162855.1911,"Tabac":98468.2848},{"Comas":"Punaauia","Ile":"Tahiti","TrancheAge":"0 - 13 ans","Sexe":"Femme","StatutMarital":"Non concerne","StatutOccupation":"Propriétaire du sol et du logement","StatutMaritalFreq":0.4842,"AgeMin":0,"AgeMax":13,"Alcool":162855.1911,"Tabac":98468.2848},{"Comas":"Punaauia","Ile":"Tahiti","TrancheAge":"0 - 13 ans","Sexe":"Homme","StatutMarital":"Non concerne","StatutOccupation":"Propriétaire du sol et du logement","StatutMaritalFreq":0.5158,"AgeMin":0,"AgeMax":13,"Alcool":162855.1911,"Tabac":98468.2848},{"Comas":"Punaauia","Ile":"Tahiti","TrancheAge":"14 - 19 ans","Sexe":"Femme","StatutMarital":"Celibataire","StatutOccupation":"Propriétaire du sol et du logement","StatutMaritalFreq":0.5068,"AgeMin":14,"AgeMax":19,"Alcool":162855.1911,"Tabac":98468.2848},{"Comas":"Punaauia","Ile":"Tahiti","TrancheAge":"14 - 19 ans","Sexe":"Homme","StatutMarital":"Celibataire","StatutOccupation":"Propriétaire du sol et du logement","StatutMaritalFreq":0.4932,"AgeMin":14,"AgeMax":19,"Alcool":1906834.6194,"Tabac":343023.5356},{"Comas":"Punaauia","Ile":"Tahiti","TrancheAge":"20 - 29 ans","Sexe":"Femme","StatutMarital":"Celibataire","StatutOccupation":"Propriétaire du sol et du logement","StatutMaritalFreq":0.5221,"AgeMin":20,"AgeMax":29,"Alcool":299146.7584,"Tabac":239757.0877},{"Comas":"Punaauia","Ile":"Tahiti","TrancheAge":"20 - 29 ans","Sexe":"Homme","StatutMarital":"Celibataire","StatutOccupation":"Propriétaire du sol et du logement","StatutMaritalFreq":0.4779,"AgeMin":20,"AgeMax":29,"Alcool":597174.5334,"Tabac":755848.0122},{"Comas":"Punaauia","Ile":"Tahiti","TrancheAge":"30 - 39 ans","Sexe":"Femme","StatutMarital":"Celibataire","StatutOccupation":"Propriétaire du sol et du logement","StatutMaritalFreq":0.5084,"AgeMin":30,"AgeMax":39,"Alcool":119511.6529,"Tabac":59585.191},{"Comas":"Punaauia","Ile":"Tahiti","TrancheAge":"30 - 39 ans","Sexe":"Homme","StatutMarital":"Celibataire","StatutOccupation":"Propriétaire du sol et du logement","StatutMaritalFreq":0.4916,"AgeMin":30,"AgeMax":39,"Alcool":82387.057,"Tabac":50187.3814},{"Comas":"Punaauia","Ile":"Tahiti","TrancheAge":"40 - 49 ans","Sexe":"Femme","StatutMarital":"Marie","StatutOccupation":"Propriétaire du sol et du logement","StatutMaritalFreq":0.501,"AgeMin":40,"AgeMax":49,"Alcool":258728.7388,"Tabac":100463.7491},{"Comas":"Punaauia","Ile":"Tahiti","TrancheAge":"40 - 49 ans","Sexe":"Homme","StatutMarital":"Celibataire","StatutOccupation":"Propriétaire du sol et du logement","StatutMaritalFreq":0.499,"AgeMin":40,"AgeMax":49,"Alcool":88397.6372,"Tabac":59166.5489},{"Comas":"Punaauia","Ile":"Tahiti","TrancheAge":"50 - 59 ans","Sexe":"Femme","StatutMarital":"Marie","StatutOccupation":"Propriétaire du sol et du logement","StatutMaritalFreq":0.492,"AgeMin":50,"AgeMax":59,"Alcool":116879.8918,"Tabac":92205.91},{"Comas":"Punaauia","Ile":"Tahiti","TrancheAge":"50 - 59 ans","Sexe":"Homme","StatutMarital":"Marie","StatutOccupation":"Propriétaire du sol et du logement","StatutMaritalFreq":0.508,"AgeMin":50,"AgeMax":59,"Alcool":78373.08,"Tabac":53006.1427},{"Comas":"Punaauia","Ile":"Tahiti","TrancheAge":"60 ans +","Sexe":"Femme","StatutMarital":"Marie","StatutOccupation":"Propriétaire du sol et du logement","StatutMaritalFreq":0.5125,"AgeMin":60,"AgeMax":150,"Alcool":183063.1415,"Tabac":108101.743},{"Comas":"Punaauia","Ile":"Tahiti","TrancheAge":"60 ans +","Sexe":"Homme","StatutMarital":"Marie","StatutOccupation":"Propriétaire du sol et du logement","StatutMaritalFreq":0.4875,"AgeMin":60,"AgeMax":150,"Alcool":56180.9158,"Tabac":45565.7456},{"Comas":"Punaauia","Ile":"Tahiti","Sexe":"Femme","StatutMarital":"Veuf,veuve","StatutOccupation":"Logé gratuitement (parents, amis, employeurs)","StatutMaritalFreq":0.5,"AgeMax":150,"Alcool":162855.1911,"Tabac":98468.2848},{"Comas":"Punaauia","Ile":"Tahiti","Sexe":"Homme","StatutMarital":"Marie","StatutOccupation":"Propriétaire du sol et du logement","StatutMaritalFreq":0.5,"AgeMax":150,"Alcool":162855.1911,"Tabac":98468.2848},{"Comas":"Tautira","Ile":"Tahiti","TrancheAge":"0 - 13 ans","Sexe":"Femme","StatutMarital":"Non concerne","StatutOccupation":"Propriétaire du sol et du logement","StatutMaritalFreq":0.5027,"AgeMin":0,"AgeMax":13,"Alcool":162855.1911,"Tabac":98468.2848},{"Comas":"Tautira","Ile":"Tahiti","TrancheAge":"0 - 13 ans","Sexe":"Homme","StatutMarital":"Non concerne","StatutOccupation":"Propriétaire du sol et du logement","StatutMaritalFreq":0.4973,"AgeMin":0,"AgeMax":13,"Alcool":162855.1911,"Tabac":98468.2848},{"Comas":"Tautira","Ile":"Tahiti","TrancheAge":"14 - 19 ans","Sexe":"Femme","StatutMarital":"Celibataire","StatutOccupation":"Propriétaire du sol et du logement","StatutMaritalFreq":0.506,"AgeMin":14,"AgeMax":19,"Alcool":162855.1911,"Tabac":98468.2848},{"Comas":"Tautira","Ile":"Tahiti","TrancheAge":"14 - 19 ans","Sexe":"Homme","StatutMarital":"Celibataire","StatutOccupation":"Propriétaire du sol et du logement","StatutMaritalFreq":0.494,"AgeMin":14,"AgeMax":19,"Alcool":162855.1911,"Tabac":98468.2848},{"Comas":"Tautira","Ile":"Tahiti","TrancheAge":"20 - 29 ans","Sexe":"Femme","StatutMarital":"Celibataire","StatutOccupation":"Propriétaire du sol et du logement","StatutMaritalFreq":0.5135,"AgeMin":20,"AgeMax":29,"Alcool":96192.4858,"Tabac":88378.7952},{"Comas":"Tautira","Ile":"Tahiti","TrancheAge":"20 - 29 ans","Sexe":"Homme","StatutMarital":"Celibataire","StatutOccupation":"Propriétaire du sol et du logement","StatutMaritalFreq":0.4865,"AgeMin":20,"AgeMax":29,"Alcool":81224.1704,"Tabac":98468.2848},{"Comas":"Tautira","Ile":"Tahiti","TrancheAge":"30 - 39 ans","Sexe":"Femme","StatutMarital":"Celibataire","StatutOccupation":"Propriétaire du sol et du logement","StatutMaritalFreq":0.5238,"AgeMin":30,"AgeMax":39,"Alcool":162855.1911,"Tabac":98468.2848},{"Comas":"Tautira","Ile":"Tahiti","TrancheAge":"30 - 39 ans","Sexe":"Homme","StatutMarital":"Celibataire","StatutOccupation":"Propriétaire du sol et du logement","StatutMaritalFreq":0.4762,"AgeMin":30,"AgeMax":39,"Alcool":92204.5983,"Tabac":28738.3851},{"Comas":"Tautira","Ile":"Tahiti","TrancheAge":"40 - 49 ans","Sexe":"Femme","StatutMarital":"Marie","StatutOccupation":"Propriétaire du sol et du logement","StatutMaritalFreq":0.4667,"AgeMin":40,"AgeMax":49,"Alcool":50869.3523,"Tabac":85767.3444},{"Comas":"Tautira","Ile":"Tahiti","TrancheAge":"40 - 49 ans","Sexe":"Homme","StatutMarital":"Marie","StatutOccupation":"Propriétaire du sol et du logement","StatutMaritalFreq":0.5333,"AgeMin":40,"AgeMax":49,"Alcool":82417.8271,"Tabac":39702.3605},{"Comas":"Tautira","Ile":"Tahiti","TrancheAge":"50 - 59 ans","Sexe":"Femme","StatutMarital":"Marie","StatutOccupation":"Propriétaire du sol et du logement","StatutMaritalFreq":0.4589,"AgeMin":50,"AgeMax":59,"Alcool":45098.0979,"Tabac":41731.3485},{"Comas":"Tautira","Ile":"Tahiti","TrancheAge":"50 - 59 ans","Sexe":"Homme","StatutMarital":"Marie","StatutOccupation":"Propriétaire du sol et du logement","StatutMaritalFreq":0.5411,"AgeMin":50,"AgeMax":59,"Alcool":89559.7532,"Tabac":98468.2848},{"Comas":"Tautira","Ile":"Tahiti","TrancheAge":"60 ans +","Sexe":"Femme","StatutMarital":"Marie","StatutOccupation":"Propriétaire du sol et du logement","StatutMaritalFreq":0.5458,"AgeMin":60,"AgeMax":150,"Alcool":25095.8681,"Tabac":52993.456},{"Comas":"Tautira","Ile":"Tahiti","TrancheAge":"60 ans +","Sexe":"Homme","StatutMarital":"Marie","StatutOccupation":"Propriétaire du sol et du logement","StatutMaritalFreq":0.4542,"AgeMin":60,"AgeMax":150,"Alcool":103613.7226,"Tabac":98468.2848},{"Comas":"Tautira","Ile":"Tahiti","Sexe":"Femme","StatutMarital":"Veuf,veuve","StatutOccupation":"Propriétaire du sol et du logement","StatutMaritalFreq":0.5,"AgeMax":150,"Alcool":162855.1911,"Tabac":98468.2848},{"Comas":"Tautira","Ile":"Tahiti","Sexe":"Homme","StatutMarital":"Veuf,veuve","StatutOccupation":"Propriétaire du sol et du logement","StatutMaritalFreq":0.5,"AgeMax":150,"Alcool":162855.1911,"Tabac":98468.2848},{"Comas":"Teahupoo","Ile":"Tahiti","TrancheAge":"0 - 13 ans","Sexe":"Femme","StatutMarital":"Non concerne","StatutOccupation":"Propriétaire du sol et du logement","StatutMaritalFreq":0.4664,"AgeMin":0,"AgeMax":13,"Alcool":162855.1911,"Tabac":98468.2848},{"Comas":"Teahupoo","Ile":"Tahiti","TrancheAge":"0 - 13 ans","Sexe":"Homme","StatutMarital":"Non concerne","StatutOccupation":"Propriétaire du sol et du logement","StatutMaritalFreq":0.5336,"AgeMin":0,"AgeMax":13,"Alcool":162855.1911,"Tabac":98468.2848},{"Comas":"Teahupoo","Ile":"Tahiti","TrancheAge":"14 - 19 ans","Sexe":"Femme","StatutMarital":"Celibataire","StatutOccupation":"Propriétaire du sol et du logement","StatutMaritalFreq":0.4722,"AgeMin":14,"AgeMax":19,"Alcool":162855.1911,"Tabac":98468.2848},{"Comas":"Teahupoo","Ile":"Tahiti","TrancheAge":"14 - 19 ans","Sexe":"Homme","StatutMarital":"Celibataire","StatutOccupation":"Propriétaire du sol et du logement","StatutMaritalFreq":0.5278,"AgeMin":14,"AgeMax":19,"Alcool":162855.1911,"Tabac":98468.2848},{"Comas":"Teahupoo","Ile":"Tahiti","TrancheAge":"20 - 29 ans","Sexe":"Femme","StatutMarital":"Celibataire","StatutOccupation":"Propriétaire du sol et du logement","StatutMaritalFreq":0.5,"AgeMin":20,"AgeMax":29,"Alcool":162855.1911,"Tabac":98468.2848},{"Comas":"Teahupoo","Ile":"Tahiti","TrancheAge":"20 - 29 ans","Sexe":"Homme","StatutMarital":"Celibataire","StatutOccupation":"Propriétaire du sol et du logement","StatutMaritalFreq":0.5,"AgeMin":20,"AgeMax":29,"Alcool":162855.1911,"Tabac":98468.2848},{"Comas":"Teahupoo","Ile":"Tahiti","TrancheAge":"30 - 39 ans","Sexe":"Femme","StatutMarital":"Celibataire","StatutOccupation":"Propriétaire du sol et du logement","StatutMaritalFreq":0.5153,"AgeMin":30,"AgeMax":39,"Alcool":162855.1911,"Tabac":98468.2848},{"Comas":"Teahupoo","Ile":"Tahiti","TrancheAge":"30 - 39 ans","Sexe":"Homme","StatutMarital":"Celibataire","StatutOccupation":"Propriétaire du sol et du logement","StatutMaritalFreq":0.4847,"AgeMin":30,"AgeMax":39,"Alcool":162855.1911,"Tabac":98468.2848},{"Comas":"Teahupoo","Ile":"Tahiti","TrancheAge":"40 - 49 ans","Sexe":"Femme","StatutMarital":"Marie","StatutOccupation":"Propriétaire du sol et du logement","StatutMaritalFreq":0.455,"AgeMin":40,"AgeMax":49,"Alcool":57060.874,"Tabac":34958.0851},{"Comas":"Teahupoo","Ile":"Tahiti","TrancheAge":"40 - 49 ans","Sexe":"Homme","StatutMarital":"Celibataire","StatutOccupation":"Propriétaire du sol et du logement","StatutMaritalFreq":0.545,"AgeMin":40,"AgeMax":49,"Alcool":63198.803,"Tabac":38718.4594},{"Comas":"Teahupoo","Ile":"Tahiti","TrancheAge":"50 - 59 ans","Sexe":"Femme","StatutMarital":"Marie","StatutOccupation":"Propriétaire du sol et du logement","StatutMaritalFreq":0.4531,"AgeMin":50,"AgeMax":59,"Alcool":28556.9015,"Tabac":37123.1836},{"Comas":"Teahupoo","Ile":"Tahiti","TrancheAge":"50 - 59 ans","Sexe":"Homme","StatutMarital":"Marie","StatutOccupation":"Propriétaire du sol et du logement","StatutMaritalFreq":0.5469,"AgeMin":50,"AgeMax":59,"Alcool":162855.1911,"Tabac":48594.2601},{"Comas":"Teahupoo","Ile":"Tahiti","TrancheAge":"60 ans +","Sexe":"Femme","StatutMarital":"Marie","StatutOccupation":"Propriétaire du sol et du logement","StatutMaritalFreq":0.5168,"AgeMin":60,"AgeMax":150,"Alcool":63450.6256,"Tabac":98468.2848},{"Comas":"Teahupoo","Ile":"Tahiti","TrancheAge":"60 ans +","Sexe":"Homme","StatutMarital":"Marie","StatutOccupation":"Propriétaire du sol et du logement","StatutMaritalFreq":0.4832,"AgeMin":60,"AgeMax":150,"Alcool":52015.505,"Tabac":31867.0627},{"Comas":"Teahupoo","Ile":"Tahiti","Sexe":"Femme","StatutMarital":"Veuf,veuve","StatutOccupation":"Propriétaire du sol et du logement","StatutMaritalFreq":1,"AgeMax":150,"Alcool":162855.1911,"Tabac":98468.2848},{"Comas":"Tiarei","Ile":"Tahiti","TrancheAge":"0 - 13 ans","Sexe":"Femme","StatutMarital":"Non concerne","StatutOccupation":"Propriétaire du sol et du logement","StatutMaritalFreq":0.531,"AgeMin":0,"AgeMax":13,"Alcool":162855.1911,"Tabac":98468.2848},{"Comas":"Tiarei","Ile":"Tahiti","TrancheAge":"0 - 13 ans","Sexe":"Homme","StatutMarital":"Non concerne","StatutOccupation":"Propriétaire du sol et du logement","StatutMaritalFreq":0.469,"AgeMin":0,"AgeMax":13,"Alcool":162855.1911,"Tabac":98468.2848},{"Comas":"Tiarei","Ile":"Tahiti","TrancheAge":"14 - 19 ans","Sexe":"Femme","StatutMarital":"Celibataire","StatutOccupation":"Propriétaire du sol et du logement","StatutMaritalFreq":0.4526,"AgeMin":14,"AgeMax":19,"Alcool":162855.1911,"Tabac":98468.2848},{"Comas":"Tiarei","Ile":"Tahiti","TrancheAge":"14 - 19 ans","Sexe":"Homme","StatutMarital":"Celibataire","StatutOccupation":"Propriétaire du sol et du logement","StatutMaritalFreq":0.5474,"AgeMin":14,"AgeMax":19,"Alcool":162855.1911,"Tabac":98468.2848},{"Comas":"Tiarei","Ile":"Tahiti","TrancheAge":"20 - 29 ans","Sexe":"Femme","StatutMarital":"Celibataire","StatutOccupation":"Propriétaire du sol et du logement","StatutMaritalFreq":0.4908,"AgeMin":20,"AgeMax":29,"Alcool":79347.3745,"Tabac":98468.2848},{"Comas":"Tiarei","Ile":"Tahiti","TrancheAge":"20 - 29 ans","Sexe":"Homme","StatutMarital":"Celibataire","StatutOccupation":"Propriétaire du sol et du logement","StatutMaritalFreq":0.5092,"AgeMin":20,"AgeMax":29,"Alcool":162855.1911,"Tabac":98468.2848},{"Comas":"Tiarei","Ile":"Tahiti","TrancheAge":"30 - 39 ans","Sexe":"Femme","StatutMarital":"Celibataire","StatutOccupation":"Propriétaire du sol et du logement","StatutMaritalFreq":0.4822,"AgeMin":30,"AgeMax":39,"Alcool":162855.1911,"Tabac":20858.1902},{"Comas":"Tiarei","Ile":"Tahiti","TrancheAge":"30 - 39 ans","Sexe":"Homme","StatutMarital":"Celibataire","StatutOccupation":"Propriétaire du sol et du logement","StatutMaritalFreq":0.5178,"AgeMin":30,"AgeMax":39,"Alcool":39085.8035,"Tabac":98468.2848},{"Comas":"Tiarei","Ile":"Tahiti","TrancheAge":"40 - 49 ans","Sexe":"Femme","StatutMarital":"Marie","StatutOccupation":"Propriétaire du sol et du logement","StatutMaritalFreq":0.4901,"AgeMin":40,"AgeMax":49,"Alcool":86535.4518,"Tabac":98468.2848},{"Comas":"Tiarei","Ile":"Tahiti","TrancheAge":"40 - 49 ans","Sexe":"Homme","StatutMarital":"Celibataire","StatutOccupation":"Propriétaire du sol et du logement","StatutMaritalFreq":0.5099,"AgeMin":40,"AgeMax":49,"Alcool":38848.9055,"Tabac":18249.9554},{"Comas":"Tiarei","Ile":"Tahiti","TrancheAge":"50 - 59 ans","Sexe":"Femme","StatutMarital":"Marie","StatutOccupation":"Propriétaire du sol et du logement","StatutMaritalFreq":0.4643,"AgeMin":50,"AgeMax":59,"Alcool":92225.6246,"Tabac":98468.2848},{"Comas":"Tiarei","Ile":"Tahiti","TrancheAge":"50 - 59 ans","Sexe":"Homme","StatutMarital":"Marie","StatutOccupation":"Propriétaire du sol et du logement","StatutMaritalFreq":0.5357,"AgeMin":50,"AgeMax":59,"Alcool":41315.4629,"Tabac":41048.2455},{"Comas":"Tiarei","Ile":"Tahiti","TrancheAge":"60 ans +","Sexe":"Femme","StatutMarital":"Marie","StatutOccupation":"Propriétaire du sol et du logement","StatutMaritalFreq":0.5046,"AgeMin":60,"AgeMax":150,"Alcool":162855.1911,"Tabac":39122.943},{"Comas":"Tiarei","Ile":"Tahiti","TrancheAge":"60 ans +","Sexe":"Homme","StatutMarital":"Marie","StatutOccupation":"Propriétaire du sol et du logement","StatutMaritalFreq":0.4954,"AgeMin":60,"AgeMax":150,"Alcool":39357.9806,"Tabac":98468.2848},{"Comas":"Tiarei","Ile":"Tahiti","Sexe":"Femme","StatutMarital":"Veuf,veuve","StatutOccupation":"Propriétaire du sol et du logement","StatutMaritalFreq":1,"AgeMax":150,"Alcool":162855.1911,"Tabac":98468.2848},{"Comas":"Toahotu","Ile":"Tahiti","TrancheAge":"0 - 13 ans","Sexe":"Femme","StatutMarital":"Non concerne","StatutOccupation":"Propriétaire du sol et du logement","StatutMaritalFreq":0.4732,"AgeMin":0,"AgeMax":13,"Alcool":162855.1911,"Tabac":98468.2848},{"Comas":"Toahotu","Ile":"Tahiti","TrancheAge":"0 - 13 ans","Sexe":"Homme","StatutMarital":"Non concerne","StatutOccupation":"Propriétaire du sol et du logement","StatutMaritalFreq":0.5268,"AgeMin":0,"AgeMax":13,"Alcool":162855.1911,"Tabac":98468.2848},{"Comas":"Toahotu","Ile":"Tahiti","TrancheAge":"14 - 19 ans","Sexe":"Femme","StatutMarital":"Celibataire","StatutOccupation":"Propriétaire du sol et du logement","StatutMaritalFreq":0.4987,"AgeMin":14,"AgeMax":19,"Alcool":162855.1911,"Tabac":98468.2848},{"Comas":"Toahotu","Ile":"Tahiti","TrancheAge":"14 - 19 ans","Sexe":"Homme","StatutMarital":"Celibataire","StatutOccupation":"Propriétaire du sol et du logement","StatutMaritalFreq":0.5013,"AgeMin":14,"AgeMax":19,"Alcool":162855.1911,"Tabac":98468.2848},{"Comas":"Toahotu","Ile":"Tahiti","TrancheAge":"20 - 29 ans","Sexe":"Femme","StatutMarital":"Celibataire","StatutOccupation":"Propriétaire du sol et du logement","StatutMaritalFreq":0.4899,"AgeMin":20,"AgeMax":29,"Alcool":162855.1911,"Tabac":98468.2848},{"Comas":"Toahotu","Ile":"Tahiti","TrancheAge":"20 - 29 ans","Sexe":"Homme","StatutMarital":"Celibataire","StatutOccupation":"Propriétaire du sol et du logement","StatutMaritalFreq":0.5101,"AgeMin":20,"AgeMax":29,"Alcool":363310.4535,"Tabac":98468.2848},{"Comas":"Toahotu","Ile":"Tahiti","TrancheAge":"30 - 39 ans","Sexe":"Femme","StatutMarital":"Celibataire","StatutOccupation":"Propriétaire du sol et du logement","StatutMaritalFreq":0.497,"AgeMin":30,"AgeMax":39,"Alcool":103069.5889,"Tabac":43015.4836},{"Comas":"Toahotu","Ile":"Tahiti","TrancheAge":"30 - 39 ans","Sexe":"Homme","StatutMarital":"Celibataire","StatutOccupation":"Propriétaire du sol et du logement","StatutMaritalFreq":0.503,"AgeMin":30,"AgeMax":39,"Alcool":129113.3426,"Tabac":114434.038},{"Comas":"Toahotu","Ile":"Tahiti","TrancheAge":"40 - 49 ans","Sexe":"Femme","StatutMarital":"Marie","StatutOccupation":"Propriétaire du sol et du logement","StatutMaritalFreq":0.5146,"AgeMin":40,"AgeMax":49,"Alcool":190597.3364,"Tabac":42803.8176},{"Comas":"Toahotu","Ile":"Tahiti","TrancheAge":"40 - 49 ans","Sexe":"Homme","StatutMarital":"Marie","StatutOccupation":"Propriétaire du sol et du logement","StatutMaritalFreq":0.4854,"AgeMin":40,"AgeMax":49,"Alcool":73344.9275,"Tabac":112019.9972},{"Comas":"Toahotu","Ile":"Tahiti","TrancheAge":"50 - 59 ans","Sexe":"Femme","StatutMarital":"Marie","StatutOccupation":"Propriétaire du sol et du logement","StatutMaritalFreq":0.459,"AgeMin":50,"AgeMax":59,"Alcool":162855.1911,"Tabac":115387.148},{"Comas":"Toahotu","Ile":"Tahiti","TrancheAge":"50 - 59 ans","Sexe":"Homme","StatutMarital":"Marie","StatutOccupation":"Propriétaire du sol et du logement","StatutMaritalFreq":0.541,"AgeMin":50,"AgeMax":59,"Alcool":77346.1181,"Tabac":31292.9877},{"Comas":"Toahotu","Ile":"Tahiti","TrancheAge":"60 ans +","Sexe":"Femme","StatutMarital":"Marie","StatutOccupation":"Propriétaire du sol et du logement","StatutMaritalFreq":0.4317,"AgeMin":60,"AgeMax":150,"Alcool":378019.6472,"Tabac":98468.2848},{"Comas":"Toahotu","Ile":"Tahiti","TrancheAge":"60 ans +","Sexe":"Homme","StatutMarital":"Marie","StatutOccupation":"Propriétaire du sol et du logement","StatutMaritalFreq":0.5683,"AgeMin":60,"AgeMax":150,"Alcool":46801.9983,"Tabac":24103.3623},{"Comas":"Toahotu","Ile":"Tahiti","Sexe":"Homme","StatutMarital":"Celibataire","StatutOccupation":"Propriétaire du sol et du logement","StatutMaritalFreq":1,"AgeMax":150,"Alcool":162855.1911,"Tabac":98468.2848},{"Comas":"Vairao","Ile":"Tahiti","TrancheAge":"0 - 13 ans","Sexe":"Femme","StatutMarital":"Non concerne","StatutOccupation":"Propriétaire du sol et du logement","StatutMaritalFreq":0.4855,"AgeMin":0,"AgeMax":13,"Alcool":162855.1911,"Tabac":98468.2848},{"Comas":"Vairao","Ile":"Tahiti","TrancheAge":"0 - 13 ans","Sexe":"Homme","StatutMarital":"Non concerne","StatutOccupation":"Propriétaire du sol et du logement","StatutMaritalFreq":0.5145,"AgeMin":0,"AgeMax":13,"Alcool":162855.1911,"Tabac":98468.2848},{"Comas":"Vairao","Ile":"Tahiti","TrancheAge":"14 - 19 ans","Sexe":"Femme","StatutMarital":"Celibataire","StatutOccupation":"Propriétaire du sol et du logement","StatutMaritalFreq":0.4721,"AgeMin":14,"AgeMax":19,"Alcool":162855.1911,"Tabac":98468.2848},{"Comas":"Vairao","Ile":"Tahiti","TrancheAge":"14 - 19 ans","Sexe":"Homme","StatutMarital":"Celibataire","StatutOccupation":"Propriétaire du sol et du logement","StatutMaritalFreq":0.5279,"AgeMin":14,"AgeMax":19,"Alcool":162855.1911,"Tabac":98468.2848},{"Comas":"Vairao","Ile":"Tahiti","TrancheAge":"20 - 29 ans","Sexe":"Femme","StatutMarital":"Celibataire","StatutOccupation":"Propriétaire du sol et du logement","StatutMaritalFreq":0.5264,"AgeMin":20,"AgeMax":29,"Alcool":162855.1911,"Tabac":98468.2848},{"Comas":"Vairao","Ile":"Tahiti","TrancheAge":"20 - 29 ans","Sexe":"Homme","StatutMarital":"Celibataire","StatutOccupation":"Propriétaire du sol et du logement","StatutMaritalFreq":0.4736,"AgeMin":20,"AgeMax":29,"Alcool":162855.1911,"Tabac":98468.2848},{"Comas":"Vairao","Ile":"Tahiti","TrancheAge":"30 - 39 ans","Sexe":"Femme","StatutMarital":"Celibataire","StatutOccupation":"Propriétaire du sol et du logement","StatutMaritalFreq":0.4776,"AgeMin":30,"AgeMax":39,"Alcool":23162.165,"Tabac":48524.4213},{"Comas":"Vairao","Ile":"Tahiti","TrancheAge":"30 - 39 ans","Sexe":"Homme","StatutMarital":"Celibataire","StatutOccupation":"Propriétaire du sol et du logement","StatutMaritalFreq":0.5224,"AgeMin":30,"AgeMax":39,"Alcool":162855.1911,"Tabac":16506.8794},{"Comas":"Vairao","Ile":"Tahiti","TrancheAge":"40 - 49 ans","Sexe":"Femme","StatutMarital":"Marie","StatutOccupation":"Propriétaire du sol et du logement","StatutMaritalFreq":0.4926,"AgeMin":40,"AgeMax":49,"Alcool":162855.1911,"Tabac":15376.3424},{"Comas":"Vairao","Ile":"Tahiti","TrancheAge":"40 - 49 ans","Sexe":"Homme","StatutMarital":"Marie","StatutOccupation":"Propriétaire du sol et du logement","StatutMaritalFreq":0.5074,"AgeMin":40,"AgeMax":49,"Alcool":15621.3739,"Tabac":11821.8959},{"Comas":"Vairao","Ile":"Tahiti","TrancheAge":"50 - 59 ans","Sexe":"Femme","StatutMarital":"Marie","StatutOccupation":"Propriétaire du sol et du logement","StatutMaritalFreq":0.4407,"AgeMin":50,"AgeMax":59,"Alcool":162855.1911,"Tabac":44738.583},{"Comas":"Vairao","Ile":"Tahiti","TrancheAge":"50 - 59 ans","Sexe":"Homme","StatutMarital":"Marie","StatutOccupation":"Propriétaire du sol et du logement","StatutMaritalFreq":0.5593,"AgeMin":50,"AgeMax":59,"Alcool":66583.0479,"Tabac":50092.2227},{"Comas":"Vairao","Ile":"Tahiti","TrancheAge":"60 ans +","Sexe":"Femme","StatutMarital":"Marie","StatutOccupation":"Propriétaire du sol et du logement","StatutMaritalFreq":0.4866,"AgeMin":60,"AgeMax":150,"Alcool":162855.1911,"Tabac":47022.0065},{"Comas":"Vairao","Ile":"Tahiti","TrancheAge":"60 ans +","Sexe":"Homme","StatutMarital":"Marie","StatutOccupation":"Propriétaire du sol et du logement","StatutMaritalFreq":0.5134,"AgeMin":60,"AgeMax":150,"Alcool":162855.1911,"Tabac":46638.2282}]